{
"meta":{"test_sets":[],"test_metrics":[],"learn_metrics":[{"best_value":"Min","name":"Logloss"}],"launch_mode":"Train","parameters":"","iteration_count":1000,"learn_sets":["learn"],"name":"experiment"},
"iterations":[
{"learn":[0.6624904861],"iteration":0,"passed_time":0.1746575507,"remaining_time":174.4828932},
{"learn":[0.634936222],"iteration":1,"passed_time":0.1979258273,"remaining_time":98.76498784},
{"learn":[0.609578766],"iteration":2,"passed_time":0.2234825659,"remaining_time":74.27070606},
{"learn":[0.5874191084],"iteration":3,"passed_time":0.2436487758,"remaining_time":60.66854517},
{"learn":[0.568750287],"iteration":4,"passed_time":0.2721648635,"remaining_time":54.16080784},
{"learn":[0.550150206],"iteration":5,"passed_time":0.2929201342,"remaining_time":48.52710223},
{"learn":[0.5329147714],"iteration":6,"passed_time":0.3142457609,"remaining_time":44.5780058},
{"learn":[0.5168366077],"iteration":7,"passed_time":0.3360063398,"remaining_time":41.66478614},
{"learn":[0.5020841414],"iteration":8,"passed_time":0.3588751969,"remaining_time":39.51614669},
{"learn":[0.4894639025],"iteration":9,"passed_time":0.3899754836,"remaining_time":38.60757287},
{"learn":[0.4785458516],"iteration":10,"passed_time":0.4594341895,"remaining_time":41.30731031},
{"learn":[0.4669728951],"iteration":11,"passed_time":0.4899792287,"remaining_time":40.34162316},
{"learn":[0.4569750007],"iteration":12,"passed_time":0.519371792,"remaining_time":39.43230451},
{"learn":[0.4470689498],"iteration":13,"passed_time":0.5428421564,"remaining_time":38.23159759},
{"learn":[0.4386597995],"iteration":14,"passed_time":0.5712624438,"remaining_time":37.51290048},
{"learn":[0.4300710172],"iteration":15,"passed_time":0.597541053,"remaining_time":36.74877476},
{"learn":[0.4230019461],"iteration":16,"passed_time":0.6193651546,"remaining_time":35.81387924},
{"learn":[0.4166097195],"iteration":17,"passed_time":0.6432303412,"remaining_time":35.09178862},
{"learn":[0.410067376],"iteration":18,"passed_time":0.6640630087,"remaining_time":34.28662166},
{"learn":[0.4039072617],"iteration":19,"passed_time":0.6866216626,"remaining_time":33.64446147},
{"learn":[0.3986324751],"iteration":20,"passed_time":0.7138881184,"remaining_time":33.28078419},
{"learn":[0.3934574376],"iteration":21,"passed_time":0.738896982,"remaining_time":32.84732947},
{"learn":[0.3880562551],"iteration":22,"passed_time":0.7710478261,"remaining_time":32.7527707},
{"learn":[0.3845399567],"iteration":23,"passed_time":0.8073596105,"remaining_time":32.83262416},
{"learn":[0.3802797829],"iteration":24,"passed_time":0.8348393205,"remaining_time":32.5587335},
{"learn":[0.3767540454],"iteration":25,"passed_time":0.8690776467,"remaining_time":32.55698569},
{"learn":[0.3738413164],"iteration":26,"passed_time":0.9113164773,"remaining_time":32.84114565},
{"learn":[0.369960574],"iteration":27,"passed_time":0.9446856802,"remaining_time":32.79408861},
{"learn":[0.3668590585],"iteration":28,"passed_time":0.9833428046,"remaining_time":32.92502977},
{"learn":[0.364717363],"iteration":29,"passed_time":1.029875903,"remaining_time":33.29932087},
{"learn":[0.3620621395],"iteration":30,"passed_time":1.065496739,"remaining_time":33.30536581},
{"learn":[0.3593746908],"iteration":31,"passed_time":1.101952514,"remaining_time":33.33406355},
{"learn":[0.3573184453],"iteration":32,"passed_time":1.135020639,"remaining_time":33.25954419},
{"learn":[0.3545179881],"iteration":33,"passed_time":1.165097973,"remaining_time":33.10248946},
{"learn":[0.3523216712],"iteration":34,"passed_time":1.190536693,"remaining_time":32.8247974},
{"learn":[0.3501153592],"iteration":35,"passed_time":1.211243832,"remaining_time":32.43441817},
{"learn":[0.3479155866],"iteration":36,"passed_time":1.235555246,"remaining_time":32.15782978},
{"learn":[0.3453058481],"iteration":37,"passed_time":1.255991951,"remaining_time":31.79642781},
{"learn":[0.3431239148],"iteration":38,"passed_time":1.289246754,"remaining_time":31.76836232},
{"learn":[0.3415311177],"iteration":39,"passed_time":1.315257355,"remaining_time":31.56617652},
{"learn":[0.3402155711],"iteration":40,"passed_time":1.341827704,"remaining_time":31.38567728},
{"learn":[0.3389727672],"iteration":41,"passed_time":1.365129366,"remaining_time":31.13795079},
{"learn":[0.3377099609],"iteration":42,"passed_time":1.389066259,"remaining_time":30.91480023},
{"learn":[0.3358223903],"iteration":43,"passed_time":1.41875106,"remaining_time":30.82559121},
{"learn":[0.3346672986],"iteration":44,"passed_time":1.443279318,"remaining_time":30.62959442},
{"learn":[0.3332600752],"iteration":45,"passed_time":1.462619197,"remaining_time":30.33345031},
{"learn":[0.3323443025],"iteration":46,"passed_time":1.493995765,"remaining_time":30.29314816},
{"learn":[0.3305142889],"iteration":47,"passed_time":1.51667446,"remaining_time":30.08071012},
{"learn":[0.3292250816],"iteration":48,"passed_time":1.538367278,"remaining_time":29.85688329},
{"learn":[0.3281042379],"iteration":49,"passed_time":1.5585992,"remaining_time":29.61338481},
{"learn":[0.3272048475],"iteration":50,"passed_time":1.579705604,"remaining_time":29.39491409},
{"learn":[0.3260539362],"iteration":51,"passed_time":1.605781257,"remaining_time":29.27462754},
{"learn":[0.3244547174],"iteration":52,"passed_time":1.626057227,"remaining_time":29.05426781},
{"learn":[0.3236639462],"iteration":53,"passed_time":1.655758699,"remaining_time":29.00643943},
{"learn":[0.3228776676],"iteration":54,"passed_time":1.677022758,"remaining_time":28.81430012},
{"learn":[0.3218933324],"iteration":55,"passed_time":1.698205392,"remaining_time":28.6268909},
{"learn":[0.3202110628],"iteration":56,"passed_time":1.729164096,"remaining_time":28.60704812},
{"learn":[0.3189092532],"iteration":57,"passed_time":1.757120053,"remaining_time":28.53805328},
{"learn":[0.3182632121],"iteration":58,"passed_time":1.781991561,"remaining_time":28.42125523},
{"learn":[0.3174607818],"iteration":59,"passed_time":1.808730961,"remaining_time":28.33678506},
{"learn":[0.3166448145],"iteration":60,"passed_time":1.830939499,"remaining_time":28.18446213},
{"learn":[0.3158378285],"iteration":61,"passed_time":1.855489541,"remaining_time":28.07176112},
{"learn":[0.3150599881],"iteration":62,"passed_time":1.8775261,"remaining_time":27.92447548},
{"learn":[0.3144854631],"iteration":63,"passed_time":1.902025362,"remaining_time":27.81712092},
{"learn":[0.3136752151],"iteration":64,"passed_time":1.924443431,"remaining_time":27.68237858},
{"learn":[0.3130336937],"iteration":65,"passed_time":1.946268417,"remaining_time":27.542647},
{"learn":[0.3123660374],"iteration":66,"passed_time":1.969760095,"remaining_time":27.4296443},
{"learn":[0.3111609945],"iteration":67,"passed_time":1.999353614,"remaining_time":27.40290541},
{"learn":[0.3103428064],"iteration":68,"passed_time":2.022275222,"remaining_time":27.28606133},
{"learn":[0.3096978972],"iteration":69,"passed_time":2.057051944,"remaining_time":27.32940439},
{"learn":[0.3091291346],"iteration":70,"passed_time":2.089658432,"remaining_time":27.34215047},
{"learn":[0.3086515355],"iteration":71,"passed_time":2.119034017,"remaining_time":27.311994},
{"learn":[0.3078900168],"iteration":72,"passed_time":2.143482832,"remaining_time":27.21929568},
{"learn":[0.3072413688],"iteration":73,"passed_time":2.167237248,"remaining_time":27.11975259},
{"learn":[0.3067037182],"iteration":74,"passed_time":2.189308405,"remaining_time":27.00147033},
{"learn":[0.306010627],"iteration":75,"passed_time":2.211503615,"remaining_time":26.88722816},
{"learn":[0.3053727497],"iteration":76,"passed_time":2.234894866,"remaining_time":26.78971378},
{"learn":[0.3047551235],"iteration":77,"passed_time":2.258436876,"remaining_time":26.69588205},
{"learn":[0.3037006698],"iteration":78,"passed_time":2.278614367,"remaining_time":26.56460547},
{"learn":[0.3027310838],"iteration":79,"passed_time":2.300232443,"remaining_time":26.45267309},
{"learn":[0.3019944567],"iteration":80,"passed_time":2.321916209,"remaining_time":26.343716},
{"learn":[0.301403929],"iteration":81,"passed_time":2.348188869,"remaining_time":26.28826075},
{"learn":[0.3009120531],"iteration":82,"passed_time":2.380074895,"remaining_time":26.29552625},
{"learn":[0.3000565493],"iteration":83,"passed_time":2.410647207,"remaining_time":26.28753383},
{"learn":[0.2996463598],"iteration":84,"passed_time":2.434007848,"remaining_time":26.2013786},
{"learn":[0.2990695896],"iteration":85,"passed_time":2.45561955,"remaining_time":26.09809615},
{"learn":[0.2985235165],"iteration":86,"passed_time":2.480424241,"remaining_time":26.03019921},
{"learn":[0.2979864479],"iteration":87,"passed_time":2.519214104,"remaining_time":26.1082189},
{"learn":[0.2974498304],"iteration":88,"passed_time":2.542966669,"remaining_time":26.02969253},
{"learn":[0.2964265184],"iteration":89,"passed_time":2.557480261,"remaining_time":25.85896708},
{"learn":[0.2959218081],"iteration":90,"passed_time":2.569359152,"remaining_time":25.6653568},
{"learn":[0.2952999775],"iteration":91,"passed_time":2.580509079,"remaining_time":25.46850264},
{"learn":[0.2947528498],"iteration":92,"passed_time":2.591656833,"remaining_time":25.27562094},
{"learn":[0.2944934206],"iteration":93,"passed_time":2.601008288,"remaining_time":25.06929265},
{"learn":[0.2938441356],"iteration":94,"passed_time":2.610120251,"remaining_time":24.86482976},
{"learn":[0.2934024448],"iteration":95,"passed_time":2.619702636,"remaining_time":24.66886649},
{"learn":[0.2928704474],"iteration":96,"passed_time":2.628586532,"remaining_time":24.4702437},
{"learn":[0.2925447151],"iteration":97,"passed_time":2.639885452,"remaining_time":24.2977212},
{"learn":[0.292269248],"iteration":98,"passed_time":2.648578424,"remaining_time":24.10473899},
{"learn":[0.2919275135],"iteration":99,"passed_time":2.658220963,"remaining_time":23.92398867},
{"learn":[0.2914709091],"iteration":100,"passed_time":2.666339177,"remaining_time":23.73305862},
{"learn":[0.2909881508],"iteration":101,"passed_time":2.676026519,"remaining_time":23.55952759},
{"learn":[0.2900613017],"iteration":102,"passed_time":2.685524625,"remaining_time":23.38752998},
{"learn":[0.2896436753],"iteration":103,"passed_time":2.694747346,"remaining_time":23.21628483},
{"learn":[0.2892947631],"iteration":104,"passed_time":2.704000197,"remaining_time":23.04838263},
{"learn":[0.2887477328],"iteration":105,"passed_time":2.712745604,"remaining_time":22.87919406},
{"learn":[0.2884022007],"iteration":106,"passed_time":2.72320539,"remaining_time":22.72731228},
{"learn":[0.2879718405],"iteration":107,"passed_time":2.733091455,"remaining_time":22.57331091},
{"learn":[0.2876072442],"iteration":108,"passed_time":2.7427027,"remaining_time":22.41970739},
{"learn":[0.2871732264],"iteration":109,"passed_time":2.751821493,"remaining_time":22.26473754},
{"learn":[0.2869975818],"iteration":110,"passed_time":2.760278936,"remaining_time":22.10709887},
{"learn":[0.2866395577],"iteration":111,"passed_time":2.769571303,"remaining_time":21.9587439},
{"learn":[0.2859291568],"iteration":112,"passed_time":2.779658425,"remaining_time":21.8190887},
{"learn":[0.2854635944],"iteration":113,"passed_time":2.789567408,"remaining_time":21.68032213},
{"learn":[0.2850408919],"iteration":114,"passed_time":2.798563032,"remaining_time":21.53676768},
{"learn":[0.2843766032],"iteration":115,"passed_time":2.807627049,"remaining_time":21.39605441},
{"learn":[0.2840842522],"iteration":116,"passed_time":2.817131374,"remaining_time":21.26091456},
{"learn":[0.2836855347],"iteration":117,"passed_time":2.825436543,"remaining_time":21.11894094},
{"learn":[0.2833471047],"iteration":118,"passed_time":2.834657881,"remaining_time":20.98599658},
{"learn":[0.2830421796],"iteration":119,"passed_time":2.843310395,"remaining_time":20.85094289},
{"learn":[0.2825611289],"iteration":120,"passed_time":2.852823216,"remaining_time":20.72422816},
{"learn":[0.2822513859],"iteration":121,"passed_time":2.861898515,"remaining_time":20.59628603},
{"learn":[0.2819519138],"iteration":122,"passed_time":2.871047042,"remaining_time":20.47079883},
{"learn":[0.2815979502],"iteration":123,"passed_time":2.879958828,"remaining_time":20.34551559},
{"learn":[0.2811495191],"iteration":124,"passed_time":2.888810863,"remaining_time":20.22167604},
{"learn":[0.2807375839],"iteration":125,"passed_time":2.898909704,"remaining_time":20.10831017},
{"learn":[0.2804647661],"iteration":126,"passed_time":2.906469502,"remaining_time":19.97911713},
{"learn":[0.2801160025],"iteration":127,"passed_time":2.914976493,"remaining_time":19.85827736},
{"learn":[0.2797825443],"iteration":128,"passed_time":2.922207725,"remaining_time":19.73056534},
{"learn":[0.2790663496],"iteration":129,"passed_time":2.930425386,"remaining_time":19.61130835},
{"learn":[0.2787846374],"iteration":130,"passed_time":2.937759459,"remaining_time":19.48788527},
{"learn":[0.2782832213],"iteration":131,"passed_time":2.946536977,"remaining_time":19.37571285},
{"learn":[0.2780543855],"iteration":132,"passed_time":2.95417464,"remaining_time":19.25766476},
{"learn":[0.2777284402],"iteration":133,"passed_time":2.962735792,"remaining_time":19.1472328},
{"learn":[0.2775346214],"iteration":134,"passed_time":2.970762623,"remaining_time":19.03488643},
{"learn":[0.2772018736],"iteration":135,"passed_time":2.979133178,"remaining_time":18.92625784},
{"learn":[0.2768581305],"iteration":136,"passed_time":2.986579989,"remaining_time":18.81327394},
{"learn":[0.2765164588],"iteration":137,"passed_time":2.994487342,"remaining_time":18.70469629},
{"learn":[0.2761598114],"iteration":138,"passed_time":3.002180534,"remaining_time":18.59624057},
{"learn":[0.2757734617],"iteration":139,"passed_time":3.009773478,"remaining_time":18.48860851},
{"learn":[0.2752462124],"iteration":140,"passed_time":3.017347776,"remaining_time":18.38228184},
{"learn":[0.2749897914],"iteration":141,"passed_time":3.02531105,"remaining_time":18.27969634},
{"learn":[0.2746303084],"iteration":142,"passed_time":3.033668937,"remaining_time":18.18079915},
{"learn":[0.2744213084],"iteration":143,"passed_time":3.041700514,"remaining_time":18.08121972},
{"learn":[0.2738756855],"iteration":144,"passed_time":3.049408403,"remaining_time":17.98099438},
{"learn":[0.2736395673],"iteration":145,"passed_time":3.057152053,"remaining_time":17.88224557},
{"learn":[0.2733124029],"iteration":146,"passed_time":3.064487356,"remaining_time":17.78236541},
{"learn":[0.2730041736],"iteration":147,"passed_time":3.072278113,"remaining_time":17.68635779},
{"learn":[0.2727574106],"iteration":148,"passed_time":3.081003963,"remaining_time":17.59687499},
{"learn":[0.2725817946],"iteration":149,"passed_time":3.089419529,"remaining_time":17.50671067},
{"learn":[0.272391234],"iteration":150,"passed_time":3.097561584,"remaining_time":17.41609129},
{"learn":[0.2720977217],"iteration":151,"passed_time":3.105578335,"remaining_time":17.32585808},
{"learn":[0.2718785172],"iteration":152,"passed_time":3.113382335,"remaining_time":17.23552182},
{"learn":[0.2717046774],"iteration":153,"passed_time":3.121848362,"remaining_time":17.14989425},
{"learn":[0.271396159],"iteration":154,"passed_time":3.130488376,"remaining_time":17.06621082},
{"learn":[0.2712419522],"iteration":155,"passed_time":3.139572269,"remaining_time":16.98589099},
{"learn":[0.2709858683],"iteration":156,"passed_time":3.147379536,"remaining_time":16.89962388},
{"learn":[0.2705961734],"iteration":157,"passed_time":3.156302257,"remaining_time":16.82029431},
{"learn":[0.270317975],"iteration":158,"passed_time":3.164454799,"remaining_time":16.73777664},
{"learn":[0.2699006511],"iteration":159,"passed_time":3.173055696,"remaining_time":16.65854241},
{"learn":[0.2696875712],"iteration":160,"passed_time":3.181270492,"remaining_time":16.57817356},
{"learn":[0.2694482462],"iteration":161,"passed_time":3.189720992,"remaining_time":16.49991476},
{"learn":[0.2693029942],"iteration":162,"passed_time":3.197935604,"remaining_time":16.42130123},
{"learn":[0.2689532672],"iteration":163,"passed_time":3.206851738,"remaining_time":16.34712227},
{"learn":[0.2686776548],"iteration":164,"passed_time":3.214592327,"remaining_time":16.26778541},
{"learn":[0.2684535488],"iteration":165,"passed_time":3.224659847,"remaining_time":16.20100188},
{"learn":[0.2682055305],"iteration":166,"passed_time":3.232817735,"remaining_time":16.12537229},
{"learn":[0.2680576307],"iteration":167,"passed_time":3.241709392,"remaining_time":16.05417985},
{"learn":[0.2677957464],"iteration":168,"passed_time":3.25112114,"remaining_time":15.98628205},
{"learn":[0.267507725],"iteration":169,"passed_time":3.260635279,"remaining_time":15.91957224},
{"learn":[0.2671271955],"iteration":170,"passed_time":3.269035966,"remaining_time":15.84813343},
{"learn":[0.2666622798],"iteration":171,"passed_time":3.277410123,"remaining_time":15.77729989},
{"learn":[0.2664679647],"iteration":172,"passed_time":3.286530309,"remaining_time":15.71075471},
{"learn":[0.2662474334],"iteration":173,"passed_time":3.295979972,"remaining_time":15.64643366},
{"learn":[0.2657506961],"iteration":174,"passed_time":3.30586581,"remaining_time":15.58479596},
{"learn":[0.2654032331],"iteration":175,"passed_time":3.314714345,"remaining_time":15.51888989},
{"learn":[0.2652488426],"iteration":176,"passed_time":3.322738871,"remaining_time":15.44979713},
{"learn":[0.264857921],"iteration":177,"passed_time":3.331739534,"remaining_time":15.3858983},
{"learn":[0.264701821],"iteration":178,"passed_time":3.340233051,"remaining_time":15.32028679},
{"learn":[0.2641092813],"iteration":179,"passed_time":3.349226431,"remaining_time":15.25758708},
{"learn":[0.2634867933],"iteration":180,"passed_time":3.359803802,"remaining_time":15.20264814},
{"learn":[0.2632718842],"iteration":181,"passed_time":3.368191303,"remaining_time":15.13835432},
{"learn":[0.2630667003],"iteration":182,"passed_time":3.376444737,"remaining_time":15.07407295},
{"learn":[0.2625838381],"iteration":183,"passed_time":3.384519581,"remaining_time":15.00960858},
{"learn":[0.2624232984],"iteration":184,"passed_time":3.392127052,"remaining_time":14.94369485},
{"learn":[0.2622162696],"iteration":185,"passed_time":3.400622197,"remaining_time":14.88229284},
{"learn":[0.2619962185],"iteration":186,"passed_time":3.408979429,"remaining_time":14.82085709},
{"learn":[0.2617815398],"iteration":187,"passed_time":3.418662825,"remaining_time":14.7657139},
{"learn":[0.2615758326],"iteration":188,"passed_time":3.42663188,"remaining_time":14.70369553},
{"learn":[0.261348953],"iteration":189,"passed_time":3.435724671,"remaining_time":14.64703675},
{"learn":[0.2611576091],"iteration":190,"passed_time":3.443603532,"remaining_time":14.58573433},
{"learn":[0.2609024902],"iteration":191,"passed_time":3.452481678,"remaining_time":14.52919373},
{"learn":[0.2606404959],"iteration":192,"passed_time":3.460869973,"remaining_time":14.4710988},
{"learn":[0.2602207151],"iteration":193,"passed_time":3.469863358,"remaining_time":14.41603024},
{"learn":[0.2600587613],"iteration":194,"passed_time":3.477991093,"remaining_time":14.35786067},
{"learn":[0.2597608796],"iteration":195,"passed_time":3.487197477,"remaining_time":14.30462639},
{"learn":[0.259574636],"iteration":196,"passed_time":3.495794673,"remaining_time":14.24935595},
{"learn":[0.2593008538],"iteration":197,"passed_time":3.504101657,"remaining_time":14.19338146},
{"learn":[0.259057854],"iteration":198,"passed_time":3.512825287,"remaining_time":14.13956309},
{"learn":[0.258819514],"iteration":199,"passed_time":3.520531232,"remaining_time":14.08212493},
{"learn":[0.2585527591],"iteration":200,"passed_time":3.529194301,"remaining_time":14.0289863},
{"learn":[0.2584292874],"iteration":201,"passed_time":3.536952716,"remaining_time":13.9727142},
{"learn":[0.2582377703],"iteration":202,"passed_time":3.545413671,"remaining_time":13.91967831},
{"learn":[0.2579257822],"iteration":203,"passed_time":3.553418548,"remaining_time":13.86529983},
{"learn":[0.2576135958],"iteration":204,"passed_time":3.561732144,"remaining_time":13.812571},
{"learn":[0.257431758],"iteration":205,"passed_time":3.569413343,"remaining_time":13.75783589},
{"learn":[0.2571544956],"iteration":206,"passed_time":3.577470849,"remaining_time":13.70499702},
{"learn":[0.2570259606],"iteration":207,"passed_time":3.585716632,"remaining_time":13.65330564},
{"learn":[0.2567263783],"iteration":208,"passed_time":3.593491701,"remaining_time":13.6002485},
{"learn":[0.2564946732],"iteration":209,"passed_time":3.60248066,"remaining_time":13.55218915},
{"learn":[0.2562442014],"iteration":210,"passed_time":3.611131389,"remaining_time":13.50323538},
{"learn":[0.2559948906],"iteration":211,"passed_time":3.619160219,"remaining_time":13.45235025},
{"learn":[0.2558255191],"iteration":212,"passed_time":3.627187147,"remaining_time":13.40186049},
{"learn":[0.2556766041],"iteration":213,"passed_time":3.635670718,"remaining_time":13.35344479},
{"learn":[0.2555154626],"iteration":214,"passed_time":3.644767508,"remaining_time":13.30763951},
{"learn":[0.2553752742],"iteration":215,"passed_time":3.653627346,"remaining_time":13.26131407},
{"learn":[0.2550563397],"iteration":216,"passed_time":3.662343188,"remaining_time":13.21481436},
{"learn":[0.2547882896],"iteration":217,"passed_time":3.671630207,"remaining_time":13.17071019},
{"learn":[0.2546637503],"iteration":218,"passed_time":3.680685241,"remaining_time":13.12609668},
{"learn":[0.2544057753],"iteration":219,"passed_time":3.690008587,"remaining_time":13.08275772},
{"learn":[0.2542161191],"iteration":220,"passed_time":3.698615504,"remaining_time":13.03720126},
{"learn":[0.2539683996],"iteration":221,"passed_time":3.707822378,"remaining_time":12.99408022},
{"learn":[0.2538150623],"iteration":222,"passed_time":3.717669102,"remaining_time":12.95349279},
{"learn":[0.2535398745],"iteration":223,"passed_time":3.72670594,"remaining_time":12.91037415},
{"learn":[0.2534081534],"iteration":224,"passed_time":3.73512059,"remaining_time":12.86541537},
{"learn":[0.2531716339],"iteration":225,"passed_time":3.744445965,"remaining_time":12.82389901},
{"learn":[0.2530202797],"iteration":226,"passed_time":3.752980826,"remaining_time":12.77997435},
{"learn":[0.2529011285],"iteration":227,"passed_time":3.761703102,"remaining_time":12.73699471},
{"learn":[0.2526890073],"iteration":228,"passed_time":3.770104894,"remaining_time":12.69323525},
{"learn":[0.2525324495],"iteration":229,"passed_time":3.780075971,"remaining_time":12.65503695},
{"learn":[0.2523511439],"iteration":230,"passed_time":3.788105141,"remaining_time":12.61061841},
{"learn":[0.2520837331],"iteration":231,"passed_time":3.79795529,"remaining_time":12.57254165},
{"learn":[0.2519246097],"iteration":232,"passed_time":3.806226608,"remaining_time":12.52950991},
{"learn":[0.2517871167],"iteration":233,"passed_time":3.814172178,"remaining_time":12.48570892},
{"learn":[0.2516357768],"iteration":234,"passed_time":3.821591327,"remaining_time":12.44049943},
{"learn":[0.2514776128],"iteration":235,"passed_time":3.830171827,"remaining_time":12.39936981},
{"learn":[0.251095064],"iteration":236,"passed_time":3.839135765,"remaining_time":12.35974932},
{"learn":[0.2508952359],"iteration":237,"passed_time":3.847101892,"remaining_time":12.31719177},
{"learn":[0.2506010141],"iteration":238,"passed_time":3.855683063,"remaining_time":12.27688205},
{"learn":[0.2503826062],"iteration":239,"passed_time":3.864397071,"remaining_time":12.23725739},
{"learn":[0.2502818261],"iteration":240,"passed_time":3.872701315,"remaining_time":12.19659875},
{"learn":[0.2501668136],"iteration":241,"passed_time":3.880720383,"remaining_time":12.15531426},
{"learn":[0.2499248256],"iteration":242,"passed_time":3.88947448,"remaining_time":12.11659334},
{"learn":[0.2498061178],"iteration":243,"passed_time":3.897562978,"remaining_time":12.07605579},
{"learn":[0.2496061342],"iteration":244,"passed_time":3.906259026,"remaining_time":12.03765537},
{"learn":[0.2494475471],"iteration":245,"passed_time":3.914267317,"remaining_time":11.99738844},
{"learn":[0.2493213476],"iteration":246,"passed_time":3.922692646,"remaining_time":11.9586541},
{"learn":[0.2490905982],"iteration":247,"passed_time":3.930385277,"remaining_time":11.91794245},
{"learn":[0.2489212203],"iteration":248,"passed_time":3.939056605,"remaining_time":11.88044783},
{"learn":[0.2486532184],"iteration":249,"passed_time":3.947726265,"remaining_time":11.84317879},
{"learn":[0.2484044712],"iteration":250,"passed_time":3.95656932,"remaining_time":11.80665506},
{"learn":[0.2482997102],"iteration":251,"passed_time":3.963995698,"remaining_time":11.76614596},
{"learn":[0.2481294117],"iteration":252,"passed_time":3.973157054,"remaining_time":11.73102103},
{"learn":[0.2479010556],"iteration":253,"passed_time":3.981693835,"remaining_time":11.69426614},
{"learn":[0.2477027756],"iteration":254,"passed_time":3.99053747,"remaining_time":11.65862908},
{"learn":[0.2472980568],"iteration":255,"passed_time":3.998793682,"remaining_time":11.62149414},
{"learn":[0.2471010339],"iteration":256,"passed_time":4.00880631,"remaining_time":11.58966182},
{"learn":[0.2468765872],"iteration":257,"passed_time":4.01703556,"remaining_time":11.55286971},
{"learn":[0.2465695612],"iteration":258,"passed_time":4.026394966,"remaining_time":11.51953154},
{"learn":[0.2463755697],"iteration":259,"passed_time":4.035552361,"remaining_time":11.48580287},
{"learn":[0.2461702168],"iteration":260,"passed_time":4.044906997,"remaining_time":11.45282096},
{"learn":[0.2459339507],"iteration":261,"passed_time":4.054042631,"remaining_time":11.41940253},
{"learn":[0.2457188962],"iteration":262,"passed_time":4.062287377,"remaining_time":11.38367223},
{"learn":[0.2453888434],"iteration":263,"passed_time":4.071592612,"remaining_time":11.35110668},
{"learn":[0.2452239739],"iteration":264,"passed_time":4.080225101,"remaining_time":11.31685075},
{"learn":[0.2450309791],"iteration":265,"passed_time":4.089797966,"remaining_time":11.28538236},
{"learn":[0.2448675536],"iteration":266,"passed_time":4.09828577,"remaining_time":11.25109914},
{"learn":[0.244652036],"iteration":267,"passed_time":4.106947496,"remaining_time":11.21748346},
{"learn":[0.2443686844],"iteration":268,"passed_time":4.115634682,"remaining_time":11.1841225},
{"learn":[0.2441151173],"iteration":269,"passed_time":4.125270818,"remaining_time":11.15350999},
{"learn":[0.2439291402],"iteration":270,"passed_time":4.134335941,"remaining_time":11.12151624},
{"learn":[0.2437145151],"iteration":271,"passed_time":4.144014462,"remaining_time":11.09133283},
{"learn":[0.2435312551],"iteration":272,"passed_time":4.152606378,"remaining_time":11.058406},
{"learn":[0.2432007894],"iteration":273,"passed_time":4.160800054,"remaining_time":11.0246016},
{"learn":[0.2429860373],"iteration":274,"passed_time":4.170225741,"remaining_time":10.9942315},
{"learn":[0.2428472994],"iteration":275,"passed_time":4.179349466,"remaining_time":10.96322106},
{"learn":[0.2426727397],"iteration":276,"passed_time":4.188165042,"remaining_time":10.93156435},
{"learn":[0.2424951239],"iteration":277,"passed_time":4.196466565,"remaining_time":10.89873691},
{"learn":[0.2423671601],"iteration":278,"passed_time":4.205777751,"remaining_time":10.86869447},
{"learn":[0.2421653958],"iteration":279,"passed_time":4.214415111,"remaining_time":10.83706743},
{"learn":[0.2420374763],"iteration":280,"passed_time":4.222141426,"remaining_time":10.8032729},
{"learn":[0.2418331495],"iteration":281,"passed_time":4.229438089,"remaining_time":10.76856932},
{"learn":[0.2414180406],"iteration":282,"passed_time":4.237997293,"remaining_time":10.73725816},
{"learn":[0.2412523131],"iteration":283,"passed_time":4.24645485,"remaining_time":10.70585096},
{"learn":[0.241088173],"iteration":284,"passed_time":4.254526391,"remaining_time":10.67363638},
{"learn":[0.240813631],"iteration":285,"passed_time":4.261945085,"remaining_time":10.63996081},
{"learn":[0.2406828146],"iteration":286,"passed_time":4.269801072,"remaining_time":10.60755458},
{"learn":[0.2404617817],"iteration":287,"passed_time":4.277082068,"remaining_time":10.57389733},
{"learn":[0.2403733272],"iteration":288,"passed_time":4.284592092,"remaining_time":10.54098608},
{"learn":[0.2400123805],"iteration":289,"passed_time":4.293271959,"remaining_time":10.51111411},
{"learn":[0.2397367039],"iteration":290,"passed_time":4.301023845,"remaining_time":10.47912682},
{"learn":[0.2395309927],"iteration":291,"passed_time":4.309228234,"remaining_time":10.4484027},
{"learn":[0.2393107788],"iteration":292,"passed_time":4.316600914,"remaining_time":10.41582541},
{"learn":[0.2390513728],"iteration":293,"passed_time":4.324476312,"remaining_time":10.38462679},
{"learn":[0.2388626382],"iteration":294,"passed_time":4.332136252,"remaining_time":10.35307138},
{"learn":[0.2386160693],"iteration":295,"passed_time":4.340591639,"remaining_time":10.3235693},
{"learn":[0.2384080215],"iteration":296,"passed_time":4.348064413,"remaining_time":10.29188311},
{"learn":[0.2383268958],"iteration":297,"passed_time":4.356208589,"remaining_time":10.26194104},
{"learn":[0.2381668275],"iteration":298,"passed_time":4.363459814,"remaining_time":10.23005127},
{"learn":[0.2379245084],"iteration":299,"passed_time":4.371899636,"remaining_time":10.20109915},
{"learn":[0.2377340825],"iteration":300,"passed_time":4.379549489,"remaining_time":10.17044881},
{"learn":[0.2375793374],"iteration":301,"passed_time":4.38770839,"remaining_time":10.14112734},
{"learn":[0.237338948],"iteration":302,"passed_time":4.395538654,"remaining_time":10.11118958},
{"learn":[0.2372135264],"iteration":303,"passed_time":4.403424432,"remaining_time":10.08152436},
{"learn":[0.2369959906],"iteration":304,"passed_time":4.411880535,"remaining_time":10.05330155},
{"learn":[0.2367888248],"iteration":305,"passed_time":4.420164008,"remaining_time":10.02481641},
{"learn":[0.2365639615],"iteration":306,"passed_time":4.427755016,"remaining_time":9.994899759},
{"learn":[0.236347505],"iteration":307,"passed_time":4.435420425,"remaining_time":9.965295241},
{"learn":[0.2362560573],"iteration":308,"passed_time":4.442900608,"remaining_time":9.935418512},
{"learn":[0.2360014377],"iteration":309,"passed_time":4.450652449,"remaining_time":9.906290935},
{"learn":[0.2358928735],"iteration":310,"passed_time":4.458165623,"remaining_time":9.876772071},
{"learn":[0.2356449533],"iteration":311,"passed_time":4.466617975,"remaining_time":9.849465278},
{"learn":[0.2355155568],"iteration":312,"passed_time":4.474109645,"remaining_time":9.820170371},
{"learn":[0.2353809386],"iteration":313,"passed_time":4.481691742,"remaining_time":9.791211895},
{"learn":[0.235235688],"iteration":314,"passed_time":4.489229386,"remaining_time":9.762292475},
{"learn":[0.2350602004],"iteration":315,"passed_time":4.497103168,"remaining_time":9.734235972},
{"learn":[0.2348185713],"iteration":316,"passed_time":4.506061331,"remaining_time":9.708643184},
{"learn":[0.2342847202],"iteration":317,"passed_time":4.513731339,"remaining_time":9.680392369},
{"learn":[0.2341401878],"iteration":318,"passed_time":4.52175947,"remaining_time":9.653035106},
{"learn":[0.2339981881],"iteration":319,"passed_time":4.529294569,"remaining_time":9.624750959},
{"learn":[0.2338668049],"iteration":320,"passed_time":4.537149009,"remaining_time":9.597271579},
{"learn":[0.2336344222],"iteration":321,"passed_time":4.544298368,"remaining_time":9.568429482},
{"learn":[0.2333268742],"iteration":322,"passed_time":4.55234011,"remaining_time":9.54159212},
{"learn":[0.232923609],"iteration":323,"passed_time":4.559627854,"remaining_time":9.513297621},
{"learn":[0.2327640888],"iteration":324,"passed_time":4.567600449,"remaining_time":9.48655478},
{"learn":[0.2326077217],"iteration":325,"passed_time":4.574878995,"remaining_time":9.458492155},
{"learn":[0.2324005479],"iteration":326,"passed_time":4.58269964,"remaining_time":9.431672348},
{"learn":[0.2322566238],"iteration":327,"passed_time":4.59007128,"remaining_time":9.404048476},
{"learn":[0.231982642],"iteration":328,"passed_time":4.598360969,"remaining_time":9.378420091},
{"learn":[0.2317020673],"iteration":329,"passed_time":4.60596577,"remaining_time":9.35150626},
{"learn":[0.2315287674],"iteration":330,"passed_time":4.61374118,"remaining_time":9.325053926},
{"learn":[0.2313375707],"iteration":331,"passed_time":4.621398637,"remaining_time":9.298476775},
{"learn":[0.2311147573],"iteration":332,"passed_time":4.629317249,"remaining_time":9.272536352},
{"learn":[0.2309353058],"iteration":333,"passed_time":4.637061895,"remaining_time":9.246356952},
{"learn":[0.2307770956],"iteration":334,"passed_time":4.644954192,"remaining_time":9.22058071},
{"learn":[0.2305620826],"iteration":335,"passed_time":4.65329073,"remaining_time":9.195788823},
{"learn":[0.2302534463],"iteration":336,"passed_time":4.662110236,"remaining_time":9.172044766},
{"learn":[0.230004178],"iteration":337,"passed_time":4.670636688,"remaining_time":9.147815053},
{"learn":[0.22982239],"iteration":338,"passed_time":4.679793633,"remaining_time":9.12490735},
{"learn":[0.2296990012],"iteration":339,"passed_time":4.688915922,"remaining_time":9.10201326},
{"learn":[0.2292437142],"iteration":340,"passed_time":4.699542799,"remaining_time":9.082107639},
{"learn":[0.2290342599],"iteration":341,"passed_time":4.708991522,"remaining_time":9.059989536},
{"learn":[0.228934584],"iteration":342,"passed_time":4.718094742,"remaining_time":9.037283514},
{"learn":[0.2287577861],"iteration":343,"passed_time":4.727162764,"remaining_time":9.014589457},
{"learn":[0.2286532577],"iteration":344,"passed_time":4.73577244,"remaining_time":8.991104198},
{"learn":[0.2284450696],"iteration":345,"passed_time":4.743914654,"remaining_time":8.966821341},
{"learn":[0.2281560468],"iteration":346,"passed_time":4.751551804,"remaining_time":8.94168106},
{"learn":[0.2280732633],"iteration":347,"passed_time":4.759717283,"remaining_time":8.917631232},
{"learn":[0.2277194618],"iteration":348,"passed_time":4.767800143,"remaining_time":8.893518319},
{"learn":[0.2274512374],"iteration":349,"passed_time":4.776443808,"remaining_time":8.870538501},
{"learn":[0.2272818776],"iteration":350,"passed_time":4.78470152,"remaining_time":8.846926743},
{"learn":[0.2270022192],"iteration":351,"passed_time":4.793850271,"remaining_time":8.825042544},
{"learn":[0.2267619344],"iteration":352,"passed_time":4.801929608,"remaining_time":8.801270414},
{"learn":[0.2265088248],"iteration":353,"passed_time":4.811032888,"remaining_time":8.779455497},
{"learn":[0.2263304147],"iteration":354,"passed_time":4.820181262,"remaining_time":8.757794123},
{"learn":[0.2261912782],"iteration":355,"passed_time":4.828429256,"remaining_time":8.734574272},
{"learn":[0.2259721708],"iteration":356,"passed_time":4.836245235,"remaining_time":8.710660185},
{"learn":[0.2256521639],"iteration":357,"passed_time":4.844359791,"remaining_time":8.687371469},
{"learn":[0.2254713451],"iteration":358,"passed_time":4.852194089,"remaining_time":8.663666884},
{"learn":[0.225269086],"iteration":359,"passed_time":4.861011849,"remaining_time":8.641798843},
{"learn":[0.2250963211],"iteration":360,"passed_time":4.869737103,"remaining_time":8.61983936},
{"learn":[0.2247744846],"iteration":361,"passed_time":4.878427925,"remaining_time":8.59789231},
{"learn":[0.2245781222],"iteration":362,"passed_time":4.886711263,"remaining_time":8.575303236},
{"learn":[0.2244293805],"iteration":363,"passed_time":4.895490406,"remaining_time":8.553659061},
{"learn":[0.2240756461],"iteration":364,"passed_time":4.903511956,"remaining_time":8.530767375},
{"learn":[0.223666994],"iteration":365,"passed_time":4.913147294,"remaining_time":8.510752417},
{"learn":[0.2234937323],"iteration":366,"passed_time":4.922455202,"remaining_time":8.490229271},
{"learn":[0.2232267217],"iteration":367,"passed_time":4.931739439,"remaining_time":8.469726429},
{"learn":[0.223074923],"iteration":368,"passed_time":4.942246946,"remaining_time":8.451376215},
{"learn":[0.2229082309],"iteration":369,"passed_time":4.951152944,"remaining_time":8.4303415},
{"learn":[0.2226685037],"iteration":370,"passed_time":4.961611245,"remaining_time":8.412003971},
{"learn":[0.2225603294],"iteration":371,"passed_time":4.97034724,"remaining_time":8.390801255},
{"learn":[0.2223445992],"iteration":372,"passed_time":4.980772674,"remaining_time":8.372505272},
{"learn":[0.2221304117],"iteration":373,"passed_time":4.99040789,"remaining_time":8.352928714},
{"learn":[0.2219647028],"iteration":374,"passed_time":5.013892779,"remaining_time":8.356487966},
{"learn":[0.2218114164],"iteration":375,"passed_time":5.041684012,"remaining_time":8.367050063},
{"learn":[0.2216534349],"iteration":376,"passed_time":5.057401897,"remaining_time":8.357457247},
{"learn":[0.221369155],"iteration":377,"passed_time":5.070356556,"remaining_time":8.343285126},
{"learn":[0.2211981482],"iteration":378,"passed_time":5.08304352,"remaining_time":8.328680807},
{"learn":[0.2210771169],"iteration":379,"passed_time":5.094175296,"remaining_time":8.311549167},
{"learn":[0.220978638],"iteration":380,"passed_time":5.104026369,"remaining_time":8.2923683},
{"learn":[0.220859673],"iteration":381,"passed_time":5.113858425,"remaining_time":8.273205515},
{"learn":[0.2207771822],"iteration":382,"passed_time":5.123169064,"remaining_time":8.253251469},
{"learn":[0.2206072957],"iteration":383,"passed_time":5.132623567,"remaining_time":8.233583639},
{"learn":[0.2201473934],"iteration":384,"passed_time":5.143400102,"remaining_time":8.216080682},
{"learn":[0.2200337257],"iteration":385,"passed_time":5.153404425,"remaining_time":8.197384242},
{"learn":[0.2197405546],"iteration":386,"passed_time":5.164609354,"remaining_time":8.180634454},
{"learn":[0.2195738302],"iteration":387,"passed_time":5.177603496,"remaining_time":8.166735411},
{"learn":[0.2194719527],"iteration":388,"passed_time":5.188973929,"remaining_time":8.150290669},
{"learn":[0.2192885909],"iteration":389,"passed_time":5.201556599,"remaining_time":8.135768014},
{"learn":[0.2191197945],"iteration":390,"passed_time":5.21172573,"remaining_time":8.117496086},
{"learn":[0.2188617723],"iteration":391,"passed_time":5.222986064,"remaining_time":8.100957976},
{"learn":[0.2186422152],"iteration":392,"passed_time":5.233334296,"remaining_time":8.083037959},
{"learn":[0.2184774173],"iteration":393,"passed_time":5.243481149,"remaining_time":8.064846641},
{"learn":[0.2182567184],"iteration":394,"passed_time":5.254080065,"remaining_time":8.047388455},
{"learn":[0.2180761637],"iteration":395,"passed_time":5.264233097,"remaining_time":8.029284824},
{"learn":[0.2178764138],"iteration":396,"passed_time":5.27382589,"remaining_time":8.010370307},
{"learn":[0.2176326821],"iteration":397,"passed_time":5.28526389,"remaining_time":7.994293622},
{"learn":[0.2173663081],"iteration":398,"passed_time":5.294099613,"remaining_time":7.97432047},
{"learn":[0.2172367673],"iteration":399,"passed_time":5.304235435,"remaining_time":7.956353153},
{"learn":[0.2170796069],"iteration":400,"passed_time":5.313209518,"remaining_time":7.936689529},
{"learn":[0.216930975],"iteration":401,"passed_time":5.322959455,"remaining_time":7.918233219},
{"learn":[0.2164404251],"iteration":402,"passed_time":5.333155039,"remaining_time":7.900480293},
{"learn":[0.2162432904],"iteration":403,"passed_time":5.342983725,"remaining_time":7.882223515},
{"learn":[0.2160650703],"iteration":404,"passed_time":5.353040416,"remaining_time":7.864343328},
{"learn":[0.2159334163],"iteration":405,"passed_time":5.36299249,"remaining_time":7.846348618},
{"learn":[0.2157686557],"iteration":406,"passed_time":5.375739344,"remaining_time":7.832465433},
{"learn":[0.215599642],"iteration":407,"passed_time":5.385823333,"remaining_time":7.814724052},
{"learn":[0.2154063053],"iteration":408,"passed_time":5.395110706,"remaining_time":7.795869016},
{"learn":[0.2152198842],"iteration":409,"passed_time":5.407146689,"remaining_time":7.781015968},
{"learn":[0.2149996139],"iteration":410,"passed_time":5.418950429,"remaining_time":7.765843803},
{"learn":[0.2147930919],"iteration":411,"passed_time":5.42855015,"remaining_time":7.747542447},
{"learn":[0.2145933388],"iteration":412,"passed_time":5.44037204,"remaining_time":7.732441617},
{"learn":[0.2144861411],"iteration":413,"passed_time":5.450289559,"remaining_time":7.714661067},
{"learn":[0.2143317936],"iteration":414,"passed_time":5.459876133,"remaining_time":7.696451898},
{"learn":[0.2140972323],"iteration":415,"passed_time":5.470493002,"remaining_time":7.679730561},
{"learn":[0.2139364079],"iteration":416,"passed_time":5.479955689,"remaining_time":7.661424861},
{"learn":[0.2137841276],"iteration":417,"passed_time":5.489814806,"remaining_time":7.643713437},
{"learn":[0.2135694438],"iteration":418,"passed_time":5.499090742,"remaining_time":7.625230838},
{"learn":[0.2133997405],"iteration":419,"passed_time":5.507460118,"remaining_time":7.605540163},
{"learn":[0.2131626252],"iteration":420,"passed_time":5.516670532,"remaining_time":7.587059948},
{"learn":[0.212904803],"iteration":421,"passed_time":5.524948147,"remaining_time":7.56734604},
{"learn":[0.2127607254],"iteration":422,"passed_time":5.533560343,"remaining_time":7.548142596},
{"learn":[0.2126091046],"iteration":423,"passed_time":5.54177699,"remaining_time":7.52845176},
{"learn":[0.2124737448],"iteration":424,"passed_time":5.550666476,"remaining_time":7.509725232},
{"learn":[0.2123405264],"iteration":425,"passed_time":5.559076426,"remaining_time":7.490398752},
{"learn":[0.2121981979],"iteration":426,"passed_time":5.568273628,"remaining_time":7.472179834},
{"learn":[0.2120464028],"iteration":427,"passed_time":5.57658571,"remaining_time":7.452820155},
{"learn":[0.2118264635],"iteration":428,"passed_time":5.58506908,"remaining_time":7.433739965},
{"learn":[0.2116318062],"iteration":429,"passed_time":5.594006194,"remaining_time":7.415310537},
{"learn":[0.2114584208],"iteration":430,"passed_time":5.60408208,"remaining_time":7.398428546},
{"learn":[0.2113211942],"iteration":431,"passed_time":5.612844177,"remaining_time":7.379850677},
{"learn":[0.2111718413],"iteration":432,"passed_time":5.622528743,"remaining_time":7.36252609},
{"learn":[0.2110260784],"iteration":433,"passed_time":5.631392602,"remaining_time":7.344166388},
{"learn":[0.2108688678],"iteration":434,"passed_time":5.64071537,"remaining_time":7.3264464},
{"learn":[0.2107852446],"iteration":435,"passed_time":5.650466394,"remaining_time":7.309318914},
{"learn":[0.2106831641],"iteration":436,"passed_time":5.658839828,"remaining_time":7.290450397},
{"learn":[0.2106046779],"iteration":437,"passed_time":5.667405634,"remaining_time":7.271876636},
{"learn":[0.2104074094],"iteration":438,"passed_time":5.675956861,"remaining_time":7.253329838},
{"learn":[0.2102586603],"iteration":439,"passed_time":5.685510738,"remaining_time":7.236104576},
{"learn":[0.2101302418],"iteration":440,"passed_time":5.695431099,"remaining_time":7.219378649},
{"learn":[0.2100086491],"iteration":441,"passed_time":5.704053659,"remaining_time":7.201045117},
{"learn":[0.2098092026],"iteration":442,"passed_time":5.712610729,"remaining_time":7.182673083},
{"learn":[0.209704743],"iteration":443,"passed_time":5.721154806,"remaining_time":7.164328991},
{"learn":[0.2096283616],"iteration":444,"passed_time":5.729841418,"remaining_time":7.146206713},
{"learn":[0.2095512523],"iteration":445,"passed_time":5.743661403,"remaining_time":7.134503178},
{"learn":[0.2094164869],"iteration":446,"passed_time":5.752683856,"remaining_time":7.116854971},
{"learn":[0.2092628636],"iteration":447,"passed_time":5.760638002,"remaining_time":7.097928967},
{"learn":[0.2091263025],"iteration":448,"passed_time":5.768716879,"remaining_time":7.0792049},
{"learn":[0.2090093222],"iteration":449,"passed_time":5.776889919,"remaining_time":7.060643234},
{"learn":[0.2088852862],"iteration":450,"passed_time":5.785281162,"remaining_time":7.042393255},
{"learn":[0.2087549244],"iteration":451,"passed_time":5.79317921,"remaining_time":7.023588954},
{"learn":[0.2085807369],"iteration":452,"passed_time":5.80146337,"remaining_time":7.005299037},
{"learn":[0.2084023242],"iteration":453,"passed_time":5.810166659,"remaining_time":6.98755726},
{"learn":[0.2082773122],"iteration":454,"passed_time":5.818341877,"remaining_time":6.969222688},
{"learn":[0.208055467],"iteration":455,"passed_time":5.826710644,"remaining_time":6.951163576},
{"learn":[0.2079031129],"iteration":456,"passed_time":5.835779016,"remaining_time":6.93397813},
{"learn":[0.2076969428],"iteration":457,"passed_time":5.84466295,"remaining_time":6.916609867},
{"learn":[0.2075378552],"iteration":458,"passed_time":5.853018706,"remaining_time":6.898656034},
{"learn":[0.2073974402],"iteration":459,"passed_time":5.861629509,"remaining_time":6.881043337},
{"learn":[0.2072781633],"iteration":460,"passed_time":5.869987693,"remaining_time":6.863174331},
{"learn":[0.2071310017],"iteration":461,"passed_time":5.878607283,"remaining_time":6.845650905},
{"learn":[0.2069798303],"iteration":462,"passed_time":5.887857271,"remaining_time":6.828897094},
{"learn":[0.2068701961],"iteration":463,"passed_time":5.897192211,"remaining_time":6.812273761},
{"learn":[0.2067088124],"iteration":464,"passed_time":5.905054005,"remaining_time":6.793986866},
{"learn":[0.2065693776],"iteration":465,"passed_time":5.914070922,"remaining_time":6.777068396},
{"learn":[0.2064134194],"iteration":466,"passed_time":5.921698718,"remaining_time":6.758598323},
{"learn":[0.2062803821],"iteration":467,"passed_time":5.931424032,"remaining_time":6.742558942},
{"learn":[0.2061522804],"iteration":468,"passed_time":5.939519204,"remaining_time":6.724700848},
{"learn":[0.2060596288],"iteration":469,"passed_time":5.947641911,"remaining_time":6.706915347},
{"learn":[0.2058742224],"iteration":470,"passed_time":5.955389984,"remaining_time":6.688750109},
{"learn":[0.2056413009],"iteration":471,"passed_time":5.963826211,"remaining_time":6.671398812},
{"learn":[0.2054597636],"iteration":472,"passed_time":5.972228303,"remaining_time":6.654047179},
{"learn":[0.2052897195],"iteration":473,"passed_time":5.981079835,"remaining_time":6.637232053},
{"learn":[0.2051417797],"iteration":474,"passed_time":5.989874081,"remaining_time":6.620387142},
{"learn":[0.2050296978],"iteration":475,"passed_time":5.998156607,"remaining_time":6.603012735},
{"learn":[0.204761022],"iteration":476,"passed_time":6.006731461,"remaining_time":6.585996969},
{"learn":[0.2045421859],"iteration":477,"passed_time":6.015709885,"remaining_time":6.569457238},
{"learn":[0.2043619188],"iteration":478,"passed_time":6.024301896,"remaining_time":6.552528785},
{"learn":[0.2040341133],"iteration":479,"passed_time":6.033002582,"remaining_time":6.535752797},
{"learn":[0.2039114133],"iteration":480,"passed_time":6.041579127,"remaining_time":6.518876438},
{"learn":[0.2037848598],"iteration":481,"passed_time":6.049202222,"remaining_time":6.501009856},
{"learn":[0.2036230058],"iteration":482,"passed_time":6.057827141,"remaining_time":6.484258037},
{"learn":[0.203489873],"iteration":483,"passed_time":6.066685396,"remaining_time":6.467788562},
{"learn":[0.203413188],"iteration":484,"passed_time":6.075112269,"remaining_time":6.450892409},
{"learn":[0.203300933],"iteration":485,"passed_time":6.083113234,"remaining_time":6.433580663},
{"learn":[0.2031633739],"iteration":486,"passed_time":6.092653291,"remaining_time":6.417928415},
{"learn":[0.2030429712],"iteration":487,"passed_time":6.101109389,"remaining_time":6.401163949},
{"learn":[0.2028764937],"iteration":488,"passed_time":6.110505515,"remaining_time":6.385415784},
{"learn":[0.2027329101],"iteration":489,"passed_time":6.118532424,"remaining_time":6.368268441},
{"learn":[0.2025038138],"iteration":490,"passed_time":6.127272868,"remaining_time":6.351897943},
{"learn":[0.2023948763],"iteration":491,"passed_time":6.13545605,"remaining_time":6.334983076},
{"learn":[0.2023191326],"iteration":492,"passed_time":6.144824546,"remaining_time":6.319322606},
{"learn":[0.2021887079],"iteration":493,"passed_time":6.153011883,"remaining_time":6.302477759},
{"learn":[0.2020388216],"iteration":494,"passed_time":6.161238057,"remaining_time":6.285707513},
{"learn":[0.2019245565],"iteration":495,"passed_time":6.169960199,"remaining_time":6.269475686},
{"learn":[0.2017566509],"iteration":496,"passed_time":6.177885556,"remaining_time":6.252467675},
{"learn":[0.2016249809],"iteration":497,"passed_time":6.19339555,"remaining_time":6.243141699},
{"learn":[0.2015199522],"iteration":498,"passed_time":6.2013368,"remaining_time":6.226191857},
{"learn":[0.2014300614],"iteration":499,"passed_time":6.209636822,"remaining_time":6.209636822},
{"learn":[0.2012366901],"iteration":500,"passed_time":6.217403265,"remaining_time":6.192583292},
{"learn":[0.2011261693],"iteration":501,"passed_time":6.22598459,"remaining_time":6.176375151},
{"learn":[0.2010526064],"iteration":502,"passed_time":6.233379172,"remaining_time":6.159024748},
{"learn":[0.2008409189],"iteration":503,"passed_time":6.242062235,"remaining_time":6.142981882},
{"learn":[0.2006335279],"iteration":504,"passed_time":6.249597136,"remaining_time":6.125842737},
{"learn":[0.2004713065],"iteration":505,"passed_time":6.257940146,"remaining_time":6.109530499},
{"learn":[0.2003270517],"iteration":506,"passed_time":6.265330597,"remaining_time":6.09232344},
{"learn":[0.2002265611],"iteration":507,"passed_time":6.273520612,"remaining_time":6.075929412},
{"learn":[0.2001140094],"iteration":508,"passed_time":6.281008963,"remaining_time":6.058890768},
{"learn":[0.1999728444],"iteration":509,"passed_time":6.289096263,"remaining_time":6.042465037},
{"learn":[0.1998189582],"iteration":510,"passed_time":6.297072732,"remaining_time":6.025965882},
{"learn":[0.199678099],"iteration":511,"passed_time":6.305674681,"remaining_time":6.01009618},
{"learn":[0.1995009983],"iteration":512,"passed_time":6.312978316,"remaining_time":5.9930223},
{"learn":[0.1993779079],"iteration":513,"passed_time":6.321313002,"remaining_time":5.976961321},
{"learn":[0.1992688109],"iteration":514,"passed_time":6.329036646,"remaining_time":5.9603549},
{"learn":[0.1991481143],"iteration":515,"passed_time":6.337274386,"remaining_time":5.944265122},
{"learn":[0.1989925164],"iteration":516,"passed_time":6.344700107,"remaining_time":5.927447102},
{"learn":[0.1988713099],"iteration":517,"passed_time":6.352845689,"remaining_time":5.911335178},
{"learn":[0.1987480329],"iteration":518,"passed_time":6.360432656,"remaining_time":5.894736238},
{"learn":[0.1986065911],"iteration":519,"passed_time":6.368746734,"remaining_time":5.878843139},
{"learn":[0.1984951701],"iteration":520,"passed_time":6.376965626,"remaining_time":5.862891621},
{"learn":[0.1982992965],"iteration":521,"passed_time":6.387802395,"remaining_time":5.849366944},
{"learn":[0.1981680386],"iteration":522,"passed_time":6.396282681,"remaining_time":5.833703324},
{"learn":[0.1980650471],"iteration":523,"passed_time":6.404884405,"remaining_time":5.818177437},
{"learn":[0.1978977924],"iteration":524,"passed_time":6.413503122,"remaining_time":5.802693301},
{"learn":[0.1976950306],"iteration":525,"passed_time":6.422964059,"remaining_time":5.787994228},
{"learn":[0.197526289],"iteration":526,"passed_time":6.432005898,"remaining_time":5.77293888},
{"learn":[0.1973953723],"iteration":527,"passed_time":6.439990773,"remaining_time":5.756961449},
{"learn":[0.1972472151],"iteration":528,"passed_time":6.44764644,"remaining_time":5.740721122},
{"learn":[0.1970508379],"iteration":529,"passed_time":6.455570492,"remaining_time":5.724751191},
{"learn":[0.196930987],"iteration":530,"passed_time":6.462934466,"remaining_time":5.708316883},
{"learn":[0.1967924371],"iteration":531,"passed_time":6.471163226,"remaining_time":5.692677425},
{"learn":[0.1966059005],"iteration":532,"passed_time":6.478904942,"remaining_time":5.676639039},
{"learn":[0.196484305],"iteration":533,"passed_time":6.487558638,"remaining_time":5.661427576},
{"learn":[0.1963489405],"iteration":534,"passed_time":6.496099772,"remaining_time":5.646142793},
{"learn":[0.1962809458],"iteration":535,"passed_time":6.504402494,"remaining_time":5.630676785},
{"learn":[0.1961592359],"iteration":536,"passed_time":6.511902237,"remaining_time":5.614545132},
{"learn":[0.1960472279],"iteration":537,"passed_time":6.520145402,"remaining_time":5.59908397},
{"learn":[0.1958418527],"iteration":538,"passed_time":6.527618345,"remaining_time":5.58299083},
{"learn":[0.1956690266],"iteration":539,"passed_time":6.536186726,"remaining_time":5.567862767},
{"learn":[0.1955832633],"iteration":540,"passed_time":6.543698826,"remaining_time":5.551862775},
{"learn":[0.1952662251],"iteration":541,"passed_time":6.551737579,"remaining_time":5.536339135},
{"learn":[0.195156329],"iteration":542,"passed_time":6.559484655,"remaining_time":5.520597583},
{"learn":[0.1950574637],"iteration":543,"passed_time":6.567471247,"remaining_time":5.505086192},
{"learn":[0.1948693805],"iteration":544,"passed_time":6.575225889,"remaining_time":5.48940877},
{"learn":[0.1947284609],"iteration":545,"passed_time":6.583420688,"remaining_time":5.474126359},
{"learn":[0.1946337916],"iteration":546,"passed_time":6.591418225,"remaining_time":5.4587065},
{"learn":[0.1945127777],"iteration":547,"passed_time":6.600557265,"remaining_time":5.444255262},
{"learn":[0.1944136173],"iteration":548,"passed_time":6.607827016,"remaining_time":5.428287767},
{"learn":[0.1942506355],"iteration":549,"passed_time":6.616705784,"remaining_time":5.413668369},
{"learn":[0.1941549374],"iteration":550,"passed_time":6.62394805,"remaining_time":5.397736252},
{"learn":[0.1940238255],"iteration":551,"passed_time":6.631676012,"remaining_time":5.382229807},
{"learn":[0.1938896086],"iteration":552,"passed_time":6.63907199,"remaining_time":5.366483146},
{"learn":[0.1937933825],"iteration":553,"passed_time":6.649593236,"remaining_time":5.353282641},
{"learn":[0.1936938394],"iteration":554,"passed_time":6.657303164,"remaining_time":5.337837672},
{"learn":[0.1935609646],"iteration":555,"passed_time":6.666491026,"remaining_time":5.323600747},
{"learn":[0.1934418803],"iteration":556,"passed_time":6.674175936,"remaining_time":5.308186606},
{"learn":[0.1932550354],"iteration":557,"passed_time":6.682787041,"remaining_time":5.293533821},
{"learn":[0.1931576958],"iteration":558,"passed_time":6.690236679,"remaining_time":5.27798636},
{"learn":[0.1930447506],"iteration":559,"passed_time":6.69853456,"remaining_time":5.263134297},
{"learn":[0.1929838037],"iteration":560,"passed_time":6.705917036,"remaining_time":5.247589267},
{"learn":[0.1928547842],"iteration":561,"passed_time":6.714156722,"remaining_time":5.23274136},
{"learn":[0.1927975076],"iteration":562,"passed_time":6.721691621,"remaining_time":5.217369873},
{"learn":[0.1926821988],"iteration":563,"passed_time":6.729834244,"remaining_time":5.202495976},
{"learn":[0.1925457542],"iteration":564,"passed_time":6.737490135,"remaining_time":5.187271166},
{"learn":[0.1923079101],"iteration":565,"passed_time":6.745463873,"remaining_time":5.172316821},
{"learn":[0.192236828],"iteration":566,"passed_time":6.752766299,"remaining_time":5.15687444},
{"learn":[0.1920717786],"iteration":567,"passed_time":6.760834374,"remaining_time":5.142043045},
{"learn":[0.191990345],"iteration":568,"passed_time":6.76821531,"remaining_time":5.126714936},
{"learn":[0.1919082011],"iteration":569,"passed_time":6.775962766,"remaining_time":5.111691209},
{"learn":[0.1918239686],"iteration":570,"passed_time":6.783383133,"remaining_time":5.096447222},
{"learn":[0.1916679989],"iteration":571,"passed_time":6.79122051,"remaining_time":5.081542619},
{"learn":[0.1915713864],"iteration":572,"passed_time":6.799046756,"remaining_time":5.066654389},
{"learn":[0.1914543933],"iteration":573,"passed_time":6.806582086,"remaining_time":5.051574858},
{"learn":[0.1913648591],"iteration":574,"passed_time":6.814367879,"remaining_time":5.036706693},
{"learn":[0.1912646343],"iteration":575,"passed_time":6.822566697,"remaining_time":5.022167152},
{"learn":[0.1911815113],"iteration":576,"passed_time":6.830826833,"remaining_time":5.007694541},
{"learn":[0.1910332209],"iteration":577,"passed_time":6.838830942,"remaining_time":4.993056501},
{"learn":[0.1909147294],"iteration":578,"passed_time":6.846927797,"remaining_time":4.978508813},
{"learn":[0.1907939741],"iteration":579,"passed_time":6.854784114,"remaining_time":4.963809186},
{"learn":[0.190665957],"iteration":580,"passed_time":6.863045692,"remaining_time":4.949425378},
{"learn":[0.1905338887],"iteration":581,"passed_time":6.872152362,"remaining_time":4.935669566},
{"learn":[0.190438348],"iteration":582,"passed_time":6.880484739,"remaining_time":4.921375877},
{"learn":[0.1903590027],"iteration":583,"passed_time":6.888230103,"remaining_time":4.906684457},
{"learn":[0.1902785577],"iteration":584,"passed_time":6.896284026,"remaining_time":4.892235676},
{"learn":[0.1902061519],"iteration":585,"passed_time":6.904293688,"remaining_time":4.877777452},
{"learn":[0.1901079141],"iteration":586,"passed_time":6.912433098,"remaining_time":4.863432487},
{"learn":[0.1900131531],"iteration":587,"passed_time":6.921108215,"remaining_time":4.849483987},
{"learn":[0.1899280667],"iteration":588,"passed_time":6.92949118,"remaining_time":4.835349533},
{"learn":[0.1898055964],"iteration":589,"passed_time":6.937803417,"remaining_time":4.821185425},
{"learn":[0.1897029636],"iteration":590,"passed_time":6.946300798,"remaining_time":4.80716925},
{"learn":[0.1895799476],"iteration":591,"passed_time":6.953970538,"remaining_time":4.792601316},
{"learn":[0.1894039296],"iteration":592,"passed_time":6.962334582,"remaining_time":4.778533179},
{"learn":[0.18923921],"iteration":593,"passed_time":6.971234749,"remaining_time":4.764850687},
{"learn":[0.1891610553],"iteration":594,"passed_time":6.979377951,"remaining_time":4.750669025},
{"learn":[0.1890538567],"iteration":595,"passed_time":6.987460634,"remaining_time":4.736466604},
{"learn":[0.1889161155],"iteration":596,"passed_time":6.995690346,"remaining_time":4.722383935},
{"learn":[0.1887281596],"iteration":597,"passed_time":7.003506374,"remaining_time":4.708042747},
{"learn":[0.1886156153],"iteration":598,"passed_time":7.012135937,"remaining_time":4.694267965},
{"learn":[0.1884811995],"iteration":599,"passed_time":7.021722772,"remaining_time":4.681148515},
{"learn":[0.1883192352],"iteration":600,"passed_time":7.03075687,"remaining_time":4.667673862},
{"learn":[0.188214621],"iteration":601,"passed_time":7.038410395,"remaining_time":4.653301225},
{"learn":[0.1880761769],"iteration":602,"passed_time":7.046860296,"remaining_time":4.639475187},
{"learn":[0.1879235677],"iteration":603,"passed_time":7.055298341,"remaining_time":4.625659177},
{"learn":[0.1877257007],"iteration":604,"passed_time":7.064342078,"remaining_time":4.612256398},
{"learn":[0.1876228589],"iteration":605,"passed_time":7.072514164,"remaining_time":4.598301288},
{"learn":[0.1874832516],"iteration":606,"passed_time":7.081696867,"remaining_time":4.585019553},
{"learn":[0.1873722711],"iteration":607,"passed_time":7.090021553,"remaining_time":4.571198106},
{"learn":[0.1872216401],"iteration":608,"passed_time":7.099645522,"remaining_time":4.558228898},
{"learn":[0.1871448703],"iteration":609,"passed_time":7.108451943,"remaining_time":4.544747963},
{"learn":[0.1870550372],"iteration":610,"passed_time":7.11694084,"remaining_time":4.531080175},
{"learn":[0.1869440396],"iteration":611,"passed_time":7.12594568,"remaining_time":4.517756412},
{"learn":[0.1868380978],"iteration":612,"passed_time":7.134189767,"remaining_time":4.50396646},
{"learn":[0.1867257361],"iteration":613,"passed_time":7.142625455,"remaining_time":4.490315026},
{"learn":[0.1866266857],"iteration":614,"passed_time":7.151170344,"remaining_time":4.476748914},
{"learn":[0.1865611122],"iteration":615,"passed_time":7.160076234,"remaining_time":4.463424146},
{"learn":[0.1863924581],"iteration":616,"passed_time":7.170160002,"remaining_time":4.450844864},
{"learn":[0.1862669151],"iteration":617,"passed_time":7.187577722,"remaining_time":4.442806941},
{"learn":[0.1861558163],"iteration":618,"passed_time":7.196976062,"remaining_time":4.429802714},
{"learn":[0.1860354433],"iteration":619,"passed_time":7.204403084,"remaining_time":4.41560189},
{"learn":[0.1859544494],"iteration":620,"passed_time":7.213087672,"remaining_time":4.402190382},
{"learn":[0.1858563268],"iteration":621,"passed_time":7.221458397,"remaining_time":4.388603334},
{"learn":[0.1857604783],"iteration":622,"passed_time":7.229948661,"remaining_time":4.37510537},
{"learn":[0.1856209913],"iteration":623,"passed_time":7.237961889,"remaining_time":4.36133601},
{"learn":[0.1854157981],"iteration":624,"passed_time":7.247207431,"remaining_time":4.348324458},
{"learn":[0.1852996079],"iteration":625,"passed_time":7.255644816,"remaining_time":4.334842111},
{"learn":[0.1852364316],"iteration":626,"passed_time":7.263688764,"remaining_time":4.321141801},
{"learn":[0.1850869363],"iteration":627,"passed_time":7.273316681,"remaining_time":4.308397779},
{"learn":[0.1849760366],"iteration":628,"passed_time":7.284255354,"remaining_time":4.296436783},
{"learn":[0.1849060141],"iteration":629,"passed_time":7.294126565,"remaining_time":4.28385211},
{"learn":[0.1848117691],"iteration":630,"passed_time":7.302273885,"remaining_time":4.27026793},
{"learn":[0.18471467],"iteration":631,"passed_time":7.311770707,"remaining_time":4.257486741},
{"learn":[0.1846112844],"iteration":632,"passed_time":7.320521452,"remaining_time":4.24428337},
{"learn":[0.1844945203],"iteration":633,"passed_time":7.3309874,"remaining_time":4.232084209},
{"learn":[0.1843913411],"iteration":634,"passed_time":7.339193701,"remaining_time":4.218591655},
{"learn":[0.1843115163],"iteration":635,"passed_time":7.346781868,"remaining_time":4.20476195},
{"learn":[0.1841807661],"iteration":636,"passed_time":7.355096761,"remaining_time":4.191365972},
{"learn":[0.1840676836],"iteration":637,"passed_time":7.362693788,"remaining_time":4.177578607},
{"learn":[0.1840021794],"iteration":638,"passed_time":7.370680828,"remaining_time":4.164030953},
{"learn":[0.1838744665],"iteration":639,"passed_time":7.378660194,"remaining_time":4.150496359},
{"learn":[0.1838209064],"iteration":640,"passed_time":7.386735521,"remaining_time":4.137032842},
{"learn":[0.1837275069],"iteration":641,"passed_time":7.394744505,"remaining_time":4.123549116},
{"learn":[0.1836238704],"iteration":642,"passed_time":7.403105405,"remaining_time":4.110277806},
{"learn":[0.1834063335],"iteration":643,"passed_time":7.410981933,"remaining_time":4.096753988},
{"learn":[0.1832706598],"iteration":644,"passed_time":7.421051185,"remaining_time":4.084454528},
{"learn":[0.1832042188],"iteration":645,"passed_time":7.42919765,"remaining_time":4.07110831},
{"learn":[0.1831392608],"iteration":646,"passed_time":7.437609252,"remaining_time":4.057922822},
{"learn":[0.1830469379],"iteration":647,"passed_time":7.44532896,"remaining_time":4.044376225},
{"learn":[0.1829483831],"iteration":648,"passed_time":7.453781243,"remaining_time":4.031243784},
{"learn":[0.1828812809],"iteration":649,"passed_time":7.461799974,"remaining_time":4.017892294},
{"learn":[0.182778543],"iteration":650,"passed_time":7.470855112,"remaining_time":4.005112802},
{"learn":[0.1826263576],"iteration":651,"passed_time":7.47931344,"remaining_time":3.992026192},
{"learn":[0.1825166034],"iteration":652,"passed_time":7.488960026,"remaining_time":3.97958519},
{"learn":[0.1823796383],"iteration":653,"passed_time":7.498330939,"remaining_time":3.967006888},
{"learn":[0.1823220726],"iteration":654,"passed_time":7.507681654,"remaining_time":3.954427741},
{"learn":[0.1820958298],"iteration":655,"passed_time":7.517244512,"remaining_time":3.941969683},
{"learn":[0.1820140818],"iteration":656,"passed_time":7.526123697,"remaining_time":3.929163513},
{"learn":[0.1819276487],"iteration":657,"passed_time":7.536184193,"remaining_time":3.916983274},
{"learn":[0.1818745705],"iteration":658,"passed_time":7.546470772,"remaining_time":3.904926454},
{"learn":[0.1817659647],"iteration":659,"passed_time":7.557576607,"remaining_time":3.89329704},
{"learn":[0.1816814204],"iteration":660,"passed_time":7.569336698,"remaining_time":3.882004752},
{"learn":[0.1815919589],"iteration":661,"passed_time":7.579241547,"remaining_time":3.869763811},
{"learn":[0.1814704403],"iteration":662,"passed_time":7.590206464,"remaining_time":3.858068745},
{"learn":[0.1813478549],"iteration":663,"passed_time":7.603403787,"remaining_time":3.847505531},
{"learn":[0.1812439075],"iteration":664,"passed_time":7.613058801,"remaining_time":3.835149922},
{"learn":[0.1811597091],"iteration":665,"passed_time":7.624186861,"remaining_time":3.823541158},
{"learn":[0.1810109211],"iteration":666,"passed_time":7.635580264,"remaining_time":3.812066309},
{"learn":[0.1809547139],"iteration":667,"passed_time":7.645004123,"remaining_time":3.799612828},
{"learn":[0.1808843344],"iteration":668,"passed_time":7.65407364,"remaining_time":3.786993086},
{"learn":[0.1807430093],"iteration":669,"passed_time":7.665194119,"remaining_time":3.775394118},
{"learn":[0.1806437268],"iteration":670,"passed_time":7.675241503,"remaining_time":3.763270424},
{"learn":[0.1805263675],"iteration":671,"passed_time":7.684921702,"remaining_time":3.750973688},
{"learn":[0.1804555359],"iteration":672,"passed_time":7.693581551,"remaining_time":3.738188956},
{"learn":[0.1803737925],"iteration":673,"passed_time":7.701662761,"remaining_time":3.725136588},
{"learn":[0.1802494366],"iteration":674,"passed_time":7.710485203,"remaining_time":3.712455839},
{"learn":[0.1801550206],"iteration":675,"passed_time":7.720265628,"remaining_time":3.700245656},
{"learn":[0.1800832877],"iteration":676,"passed_time":7.728005294,"remaining_time":3.687068995},
{"learn":[0.1799864611],"iteration":677,"passed_time":7.736661762,"remaining_time":3.674343787},
{"learn":[0.1799158618],"iteration":678,"passed_time":7.75352249,"remaining_time":3.665509159},
{"learn":[0.1798062197],"iteration":679,"passed_time":7.761050846,"remaining_time":3.652259222},
{"learn":[0.1796839575],"iteration":680,"passed_time":7.769404496,"remaining_time":3.639412679},
{"learn":[0.1795931777],"iteration":681,"passed_time":7.778028566,"remaining_time":3.626705402},
{"learn":[0.1795361333],"iteration":682,"passed_time":7.786030943,"remaining_time":3.613721536},
{"learn":[0.1794962443],"iteration":683,"passed_time":7.794261507,"remaining_time":3.600857655},
{"learn":[0.1794015368],"iteration":684,"passed_time":7.802729071,"remaining_time":3.588116288},
{"learn":[0.1793161553],"iteration":685,"passed_time":7.811008759,"remaining_time":3.575301385},
{"learn":[0.1792010274],"iteration":686,"passed_time":7.819496244,"remaining_time":3.562594359},
{"learn":[0.1790835633],"iteration":687,"passed_time":7.827634912,"remaining_time":3.549741414},
{"learn":[0.178991425],"iteration":688,"passed_time":7.835620769,"remaining_time":3.536833177},
{"learn":[0.1788797214],"iteration":689,"passed_time":7.843608056,"remaining_time":3.523939851},
{"learn":[0.1787019525],"iteration":690,"passed_time":7.851609241,"remaining_time":3.51106694},
{"learn":[0.1786364688],"iteration":691,"passed_time":7.8602405,"remaining_time":3.498488546},
{"learn":[0.1785327404],"iteration":692,"passed_time":7.868604951,"remaining_time":3.485803348},
{"learn":[0.1783315512],"iteration":693,"passed_time":7.876625437,"remaining_time":3.472978939},
{"learn":[0.1782487372],"iteration":694,"passed_time":7.884876168,"remaining_time":3.460269397},
{"learn":[0.1781038363],"iteration":695,"passed_time":7.892944005,"remaining_time":3.447492784},
{"learn":[0.1780275609],"iteration":696,"passed_time":7.900891248,"remaining_time":3.434677257},
{"learn":[0.1779514768],"iteration":697,"passed_time":7.909386559,"remaining_time":3.422112809},
{"learn":[0.1778533735],"iteration":698,"passed_time":7.917428569,"remaining_time":3.409364806},
{"learn":[0.1776365798],"iteration":699,"passed_time":7.925966476,"remaining_time":3.396842776},
{"learn":[0.177525459],"iteration":700,"passed_time":7.93370089,"remaining_time":3.383989395},
{"learn":[0.1774129571],"iteration":701,"passed_time":7.941316361,"remaining_time":3.371100108},
{"learn":[0.1772714626],"iteration":702,"passed_time":7.948980277,"remaining_time":3.358246291},
{"learn":[0.17712039],"iteration":703,"passed_time":7.956875966,"remaining_time":3.345504668},
{"learn":[0.1770500724],"iteration":704,"passed_time":7.964681192,"remaining_time":3.332738938},
{"learn":[0.1769657942],"iteration":705,"passed_time":7.972884483,"remaining_time":3.320153028},
{"learn":[0.1768941444],"iteration":706,"passed_time":7.981032316,"remaining_time":3.307556533},
{"learn":[0.1768182076],"iteration":707,"passed_time":7.988466849,"remaining_time":3.294678418},
{"learn":[0.1766865568],"iteration":708,"passed_time":7.996394085,"remaining_time":3.282017882},
{"learn":[0.1765567123],"iteration":709,"passed_time":8.004064761,"remaining_time":3.269265888},
{"learn":[0.1764342246],"iteration":710,"passed_time":8.011988006,"remaining_time":3.256630849},
{"learn":[0.1763187235],"iteration":711,"passed_time":8.020374782,"remaining_time":3.244196541},
{"learn":[0.1762300456],"iteration":712,"passed_time":8.028699405,"remaining_time":3.231748568},
{"learn":[0.1760863317],"iteration":713,"passed_time":8.036533753,"remaining_time":3.219115761},
{"learn":[0.1759808765],"iteration":714,"passed_time":8.044873125,"remaining_time":3.206697679},
{"learn":[0.1759240248],"iteration":715,"passed_time":8.052689364,"remaining_time":3.194083491},
{"learn":[0.1757751131],"iteration":716,"passed_time":8.061162973,"remaining_time":3.18174215},
{"learn":[0.1756979304],"iteration":717,"passed_time":8.069361479,"remaining_time":3.169303533},
{"learn":[0.1756152732],"iteration":718,"passed_time":8.079327474,"remaining_time":3.157567483},
{"learn":[0.1755167365],"iteration":719,"passed_time":8.087978362,"remaining_time":3.145324919},
{"learn":[0.1754501585],"iteration":720,"passed_time":8.09731045,"remaining_time":3.133355916},
{"learn":[0.1753497804],"iteration":721,"passed_time":8.106622992,"remaining_time":3.121386692},
{"learn":[0.1752587746],"iteration":722,"passed_time":8.114945417,"remaining_time":3.109045478},
{"learn":[0.1751225046],"iteration":723,"passed_time":8.124117996,"remaining_time":3.097039457},
{"learn":[0.1749948256],"iteration":724,"passed_time":8.133089469,"remaining_time":3.084964971},
{"learn":[0.1749210302],"iteration":725,"passed_time":8.141374533,"remaining_time":3.072639975},
{"learn":[0.1747853703],"iteration":726,"passed_time":8.150390563,"remaining_time":3.060600583},
{"learn":[0.1746601518],"iteration":727,"passed_time":8.159356771,"remaining_time":3.048550881},
{"learn":[0.1745426427],"iteration":728,"passed_time":8.167501504,"remaining_time":3.036204263},
{"learn":[0.1743852018],"iteration":729,"passed_time":8.175001743,"remaining_time":3.023630782},
{"learn":[0.174281031],"iteration":730,"passed_time":8.182990421,"remaining_time":3.011250921},
{"learn":[0.1742023482],"iteration":731,"passed_time":8.190321374,"remaining_time":2.998642252},
{"learn":[0.1741561613],"iteration":732,"passed_time":8.197979558,"remaining_time":2.986167179},
{"learn":[0.1740365356],"iteration":733,"passed_time":8.205492206,"remaining_time":2.973652489},
{"learn":[0.1739468165],"iteration":734,"passed_time":8.213740734,"remaining_time":2.961416727},
{"learn":[0.1738703237],"iteration":735,"passed_time":8.221485162,"remaining_time":2.949010982},
{"learn":[0.1737578072],"iteration":736,"passed_time":8.229177748,"remaining_time":2.936599386},
{"learn":[0.17368514],"iteration":737,"passed_time":8.236895988,"remaining_time":2.924209687},
{"learn":[0.1736101979],"iteration":738,"passed_time":8.245115189,"remaining_time":2.912009559},
{"learn":[0.1735226558],"iteration":739,"passed_time":8.25290624,"remaining_time":2.89966976},
{"learn":[0.1734089014],"iteration":740,"passed_time":8.260304698,"remaining_time":2.887205016},
{"learn":[0.1733228859],"iteration":741,"passed_time":8.268110093,"remaining_time":2.874895423},
{"learn":[0.1732544286],"iteration":742,"passed_time":8.275584277,"remaining_time":2.86248339},
{"learn":[0.1731809843],"iteration":743,"passed_time":8.28371398,"remaining_time":2.850310187},
{"learn":[0.1730832015],"iteration":744,"passed_time":8.29108083,"remaining_time":2.837886727},
{"learn":[0.1729909098],"iteration":745,"passed_time":8.299812978,"remaining_time":2.825941684},
{"learn":[0.1729184777],"iteration":746,"passed_time":8.307092937,"remaining_time":2.813513405},
{"learn":[0.1728261932],"iteration":747,"passed_time":8.315611037,"remaining_time":2.801516018},
{"learn":[0.1727636174],"iteration":748,"passed_time":8.323168421,"remaining_time":2.789205973},
{"learn":[0.1726836405],"iteration":749,"passed_time":8.331469884,"remaining_time":2.777156628},
{"learn":[0.1725447723],"iteration":750,"passed_time":8.3394739,"remaining_time":2.765018643},
{"learn":[0.1724372418],"iteration":751,"passed_time":8.348231228,"remaining_time":2.753140086},
{"learn":[0.1723400201],"iteration":752,"passed_time":8.355935345,"remaining_time":2.740924343},
{"learn":[0.1722312705],"iteration":753,"passed_time":8.36458118,"remaining_time":2.729027812},
{"learn":[0.172140291],"iteration":754,"passed_time":8.372821617,"remaining_time":2.717008339},
{"learn":[0.1720616354],"iteration":755,"passed_time":8.382083285,"remaining_time":2.705328467},
{"learn":[0.1719708182],"iteration":756,"passed_time":8.390525353,"remaining_time":2.69339189},
{"learn":[0.1718413863],"iteration":757,"passed_time":8.399560949,"remaining_time":2.681654023},
{"learn":[0.1717596121],"iteration":758,"passed_time":8.407671246,"remaining_time":2.669629473},
{"learn":[0.171691324],"iteration":759,"passed_time":8.41523597,"remaining_time":2.657442938},
{"learn":[0.1716238771],"iteration":760,"passed_time":8.42281199,"remaining_time":2.645272097},
{"learn":[0.1714950286],"iteration":761,"passed_time":8.431524102,"remaining_time":2.633468158},
{"learn":[0.171426492],"iteration":762,"passed_time":8.438986187,"remaining_time":2.621284045},
{"learn":[0.1713688765],"iteration":763,"passed_time":8.447004054,"remaining_time":2.609283975},
{"learn":[0.1712764028],"iteration":764,"passed_time":8.454435107,"remaining_time":2.597114052},
{"learn":[0.1712165858],"iteration":765,"passed_time":8.462584191,"remaining_time":2.58517585},
{"learn":[0.1711637091],"iteration":766,"passed_time":8.471001436,"remaining_time":2.573328989},
{"learn":[0.1711064716],"iteration":767,"passed_time":8.479630908,"remaining_time":2.56155517},
{"learn":[0.1710045831],"iteration":768,"passed_time":8.486743851,"remaining_time":2.549333979},
{"learn":[0.1708870494],"iteration":769,"passed_time":8.494499388,"remaining_time":2.537317999},
{"learn":[0.1708254352],"iteration":770,"passed_time":8.501826516,"remaining_time":2.525185827},
{"learn":[0.1707587539],"iteration":771,"passed_time":8.511236864,"remaining_time":2.513681353},
{"learn":[0.1706927917],"iteration":772,"passed_time":8.519055522,"remaining_time":2.501714882},
{"learn":[0.1705903666],"iteration":773,"passed_time":8.527401436,"remaining_time":2.489913081},
{"learn":[0.170469001],"iteration":774,"passed_time":8.535163901,"remaining_time":2.47795081},
{"learn":[0.1703702066],"iteration":775,"passed_time":8.543571539,"remaining_time":2.466185599},
{"learn":[0.1702864095],"iteration":776,"passed_time":8.550869746,"remaining_time":2.454110622},
{"learn":[0.1701802879],"iteration":777,"passed_time":8.558966961,"remaining_time":2.442275919},
{"learn":[0.1700782367],"iteration":778,"passed_time":8.566415372,"remaining_time":2.430266749},
{"learn":[0.1700203414],"iteration":779,"passed_time":8.574740858,"remaining_time":2.418516652},
{"learn":[0.1699065022],"iteration":780,"passed_time":8.581953053,"remaining_time":2.406463148},
{"learn":[0.1698527741],"iteration":781,"passed_time":8.58962496,"remaining_time":2.394550181},
{"learn":[0.169743807],"iteration":782,"passed_time":8.598402855,"remaining_time":2.382954559},
{"learn":[0.1696635297],"iteration":783,"passed_time":8.606337934,"remaining_time":2.371133921},
{"learn":[0.1695699695],"iteration":784,"passed_time":8.61385553,"remaining_time":2.359208839},
{"learn":[0.1694988732],"iteration":785,"passed_time":8.622024537,"remaining_time":2.347472329},
{"learn":[0.1694300124],"iteration":786,"passed_time":8.629968551,"remaining_time":2.335683992},
{"learn":[0.1693216373],"iteration":787,"passed_time":8.638213072,"remaining_time":2.323986258},
{"learn":[0.1692372592],"iteration":788,"passed_time":8.645958091,"remaining_time":2.312163697},
{"learn":[0.1691902276],"iteration":789,"passed_time":8.654538817,"remaining_time":2.30057361},
{"learn":[0.1691468761],"iteration":790,"passed_time":8.662059397,"remaining_time":2.288711016},
{"learn":[0.1690564163],"iteration":791,"passed_time":8.670126105,"remaining_time":2.277002815},
{"learn":[0.1688447453],"iteration":792,"passed_time":8.677632689,"remaining_time":2.265157587},
{"learn":[0.1687607726],"iteration":793,"passed_time":8.685231411,"remaining_time":2.253347192},
{"learn":[0.1686933463],"iteration":794,"passed_time":8.693065916,"remaining_time":2.241608192},
{"learn":[0.1686656961],"iteration":795,"passed_time":8.700373376,"remaining_time":2.229743931},
{"learn":[0.1685707059],"iteration":796,"passed_time":8.708398054,"remaining_time":2.218073783},
{"learn":[0.1684668533],"iteration":797,"passed_time":8.715820157,"remaining_time":2.20626024},
{"learn":[0.1683737351],"iteration":798,"passed_time":8.724129047,"remaining_time":2.194680774},
{"learn":[0.1683180182],"iteration":799,"passed_time":8.731612792,"remaining_time":2.182903198},
{"learn":[0.1682538421],"iteration":800,"passed_time":8.740157526,"remaining_time":2.171399935},
{"learn":[0.1681215523],"iteration":801,"passed_time":8.748739086,"remaining_time":2.159913141},
{"learn":[0.1679848676],"iteration":802,"passed_time":8.758201042,"remaining_time":2.148649571},
{"learn":[0.1678985235],"iteration":803,"passed_time":8.765771261,"remaining_time":2.136929312},
{"learn":[0.167843699],"iteration":804,"passed_time":8.773776415,"remaining_time":2.125324722},
{"learn":[0.1677632629],"iteration":805,"passed_time":8.781218602,"remaining_time":2.113593559},
{"learn":[0.1676917916],"iteration":806,"passed_time":8.789408777,"remaining_time":2.102051913},
{"learn":[0.1676361854],"iteration":807,"passed_time":8.796565778,"remaining_time":2.090273056},
{"learn":[0.1675313577],"iteration":808,"passed_time":8.804467714,"remaining_time":2.0786815},
{"learn":[0.1674452883],"iteration":809,"passed_time":8.812153068,"remaining_time":2.06704825},
{"learn":[0.1673691362],"iteration":810,"passed_time":8.819684474,"remaining_time":2.05538886},
{"learn":[0.1672657815],"iteration":811,"passed_time":8.826903192,"remaining_time":2.043667241},
{"learn":[0.1672135912],"iteration":812,"passed_time":8.834808871,"remaining_time":2.03211471},
{"learn":[0.1671589111],"iteration":813,"passed_time":8.842042597,"remaining_time":2.020417596},
{"learn":[0.1670667737],"iteration":814,"passed_time":8.850123138,"remaining_time":2.008923657},
{"learn":[0.166876383],"iteration":815,"passed_time":8.858116616,"remaining_time":1.997418453},
{"learn":[0.1667891746],"iteration":816,"passed_time":8.866229154,"remaining_time":1.985948513},
{"learn":[0.1666844392],"iteration":817,"passed_time":8.873720985,"remaining_time":1.974348679},
{"learn":[0.1665492619],"iteration":818,"passed_time":8.882442493,"remaining_time":1.963030636},
{"learn":[0.1664764296],"iteration":819,"passed_time":8.890405561,"remaining_time":1.95155244},
{"learn":[0.1664105747],"iteration":820,"passed_time":8.898252033,"remaining_time":1.940057386},
{"learn":[0.1663422165],"iteration":821,"passed_time":8.906070814,"remaining_time":1.928565213},
{"learn":[0.1662453331],"iteration":822,"passed_time":8.913335931,"remaining_time":1.916962892},
{"learn":[0.1661715168],"iteration":823,"passed_time":8.921877501,"remaining_time":1.905643738},
{"learn":[0.1660536828],"iteration":824,"passed_time":8.929244018,"remaining_time":1.894082064},
{"learn":[0.1659546024],"iteration":825,"passed_time":8.937444371,"remaining_time":1.882706199},
{"learn":[0.1658359626],"iteration":826,"passed_time":8.945314249,"remaining_time":1.871268882},
{"learn":[0.1657493907],"iteration":827,"passed_time":8.954864716,"remaining_time":1.860189289},
{"learn":[0.1656412096],"iteration":828,"passed_time":8.962713495,"remaining_time":1.848762373},
{"learn":[0.165515501],"iteration":829,"passed_time":8.970828258,"remaining_time":1.837398559},
{"learn":[0.1654541466],"iteration":830,"passed_time":8.978269613,"remaining_time":1.825905613},
{"learn":[0.1654009919],"iteration":831,"passed_time":8.986671302,"remaining_time":1.814616321},
{"learn":[0.1653124732],"iteration":832,"passed_time":8.99429368,"remaining_time":1.803177725},
{"learn":[0.1652416073],"iteration":833,"passed_time":9.002713099,"remaining_time":1.791906924},
{"learn":[0.165149802],"iteration":834,"passed_time":9.010211843,"remaining_time":1.780461023},
{"learn":[0.1650669942],"iteration":835,"passed_time":9.018725922,"remaining_time":1.769223746},
{"learn":[0.1649549677],"iteration":836,"passed_time":9.026492945,"remaining_time":1.757847491},
{"learn":[0.1648503475],"iteration":837,"passed_time":9.034917309,"remaining_time":1.746606926},
{"learn":[0.164790988],"iteration":838,"passed_time":9.042413761,"remaining_time":1.735195013},
{"learn":[0.1647026673],"iteration":839,"passed_time":9.051603009,"remaining_time":1.724114859},
{"learn":[0.1645547834],"iteration":840,"passed_time":9.059342373,"remaining_time":1.712765086},
{"learn":[0.1644710091],"iteration":841,"passed_time":9.067816621,"remaining_time":1.701561789},
{"learn":[0.1643965596],"iteration":842,"passed_time":9.075216612,"remaining_time":1.690164897},
{"learn":[0.1643132066],"iteration":843,"passed_time":9.084678592,"remaining_time":1.679158602},
{"learn":[0.1642151175],"iteration":844,"passed_time":9.092344498,"remaining_time":1.667826506},
{"learn":[0.1641528263],"iteration":845,"passed_time":9.100458589,"remaining_time":1.65658466},
{"learn":[0.1640989449],"iteration":846,"passed_time":9.107579293,"remaining_time":1.645170758},
{"learn":[0.1640398478],"iteration":847,"passed_time":9.115607879,"remaining_time":1.633929714},
{"learn":[0.1639471982],"iteration":848,"passed_time":9.123075836,"remaining_time":1.622596527},
{"learn":[0.1638825148],"iteration":849,"passed_time":9.131242098,"remaining_time":1.611395664},
{"learn":[0.1637813792],"iteration":850,"passed_time":9.138508501,"remaining_time":1.600044379},
{"learn":[0.1637085901],"iteration":851,"passed_time":9.146406525,"remaining_time":1.588812401},
{"learn":[0.1636593165],"iteration":852,"passed_time":9.153851769,"remaining_time":1.577510211},
{"learn":[0.1635716452],"iteration":853,"passed_time":9.16157889,"remaining_time":1.566265243},
{"learn":[0.1634663039],"iteration":854,"passed_time":9.169314411,"remaining_time":1.555029929},
{"learn":[0.163354647],"iteration":855,"passed_time":9.17734069,"remaining_time":1.543851705},
{"learn":[0.1632837382],"iteration":856,"passed_time":9.184775164,"remaining_time":1.532582087},
{"learn":[0.1632123155],"iteration":857,"passed_time":9.192510982,"remaining_time":1.521371281},
{"learn":[0.1631427397],"iteration":858,"passed_time":9.200012071,"remaining_time":1.510130037},
{"learn":[0.16305883],"iteration":859,"passed_time":9.207775256,"remaining_time":1.498940158},
{"learn":[0.1629895917],"iteration":860,"passed_time":9.215689207,"remaining_time":1.487782578},
{"learn":[0.1628981557],"iteration":861,"passed_time":9.222985622,"remaining_time":1.476533661},
{"learn":[0.1628052726],"iteration":862,"passed_time":9.231260677,"remaining_time":1.465449262},
{"learn":[0.1626696766],"iteration":863,"passed_time":9.238700145,"remaining_time":1.454239838},
{"learn":[0.1625971296],"iteration":864,"passed_time":9.246633566,"remaining_time":1.443116221},
{"learn":[0.1625416946],"iteration":865,"passed_time":9.254064078,"remaining_time":1.431922155},
{"learn":[0.1624619187],"iteration":866,"passed_time":9.263293265,"remaining_time":1.421012692},
{"learn":[0.1624145762],"iteration":867,"passed_time":9.270780064,"remaining_time":1.40984213},
{"learn":[0.1622860721],"iteration":868,"passed_time":9.27941046,"remaining_time":1.39885244},
{"learn":[0.1622173985],"iteration":869,"passed_time":9.287704291,"remaining_time":1.387817883},
{"learn":[0.1621541593],"iteration":870,"passed_time":9.295988737,"remaining_time":1.376788229},
{"learn":[0.1620592903],"iteration":871,"passed_time":9.303472857,"remaining_time":1.365647392},
{"learn":[0.1619917726],"iteration":872,"passed_time":9.311282559,"remaining_time":1.354562297},
{"learn":[0.1619325113],"iteration":873,"passed_time":9.318448001,"remaining_time":1.343391817},
{"learn":[0.1618410435],"iteration":874,"passed_time":9.326381102,"remaining_time":1.332340157},
{"learn":[0.161757057],"iteration":875,"passed_time":9.333504685,"remaining_time":1.321181028},
{"learn":[0.1616339044],"iteration":876,"passed_time":9.34151796,"remaining_time":1.310155883},
{"learn":[0.1615647768],"iteration":877,"passed_time":9.34890867,"remaining_time":1.299051091},
{"learn":[0.1615324491],"iteration":878,"passed_time":9.357364595,"remaining_time":1.288101383},
{"learn":[0.1614831089],"iteration":879,"passed_time":9.36571827,"remaining_time":1.2771434},
{"learn":[0.1614283189],"iteration":880,"passed_time":9.373613623,"remaining_time":1.266129422},
{"learn":[0.161392224],"iteration":881,"passed_time":9.380836443,"remaining_time":1.25503254},
{"learn":[0.1613033321],"iteration":882,"passed_time":9.388489197,"remaining_time":1.2440014},
{"learn":[0.1612276249],"iteration":883,"passed_time":9.396377297,"remaining_time":1.233008786},
{"learn":[0.1611654615],"iteration":884,"passed_time":9.404008933,"remaining_time":1.221989861},
{"learn":[0.1610485011],"iteration":885,"passed_time":9.411817148,"remaining_time":1.211001303},
{"learn":[0.1609161697],"iteration":886,"passed_time":9.419118436,"remaining_time":1.199955336},
{"learn":[0.1608165193],"iteration":887,"passed_time":9.427425129,"remaining_time":1.189044611},
{"learn":[0.1607566115],"iteration":888,"passed_time":9.435107781,"remaining_time":1.178061826},
{"learn":[0.1607281685],"iteration":889,"passed_time":9.443124154,"remaining_time":1.167127704},
{"learn":[0.1606794851],"iteration":890,"passed_time":9.450898726,"remaining_time":1.156170551},
{"learn":[0.1606299114],"iteration":891,"passed_time":9.459311847,"remaining_time":1.145297847},
{"learn":[0.160572779],"iteration":892,"passed_time":9.466731093,"remaining_time":1.134311564},
{"learn":[0.1605005999],"iteration":893,"passed_time":9.474712744,"remaining_time":1.123399945},
{"learn":[0.1604308201],"iteration":894,"passed_time":9.482356176,"remaining_time":1.112455194},
{"learn":[0.1603483966],"iteration":895,"passed_time":9.490124717,"remaining_time":1.101532333},
{"learn":[0.160284116],"iteration":896,"passed_time":9.498070546,"remaining_time":1.090636863},
{"learn":[0.1602106108],"iteration":897,"passed_time":9.505648448,"remaining_time":1.079706171},
{"learn":[0.1601524424],"iteration":898,"passed_time":9.51416058,"remaining_time":1.068887896},
{"learn":[0.1600092955],"iteration":899,"passed_time":9.521826903,"remaining_time":1.057980767},
{"learn":[0.1599210972],"iteration":900,"passed_time":9.530203547,"remaining_time":1.04715888},
{"learn":[0.1598497457],"iteration":901,"passed_time":9.537696034,"remaining_time":1.036246354},
{"learn":[0.159790591],"iteration":902,"passed_time":9.545987543,"remaining_time":1.025427233},
{"learn":[0.1597022919],"iteration":903,"passed_time":9.553780472,"remaining_time":1.014560758},
{"learn":[0.1596349329],"iteration":904,"passed_time":9.56261564,"remaining_time":1.003810482},
{"learn":[0.159565834],"iteration":905,"passed_time":9.570056473,"remaining_time":0.9929197665},
{"learn":[0.1594898726],"iteration":906,"passed_time":9.578368234,"remaining_time":0.9821259601},
{"learn":[0.159385583],"iteration":907,"passed_time":9.585927574,"remaining_time":0.9712613841},
{"learn":[0.1593322448],"iteration":908,"passed_time":9.593882143,"remaining_time":0.9604436468},
{"learn":[0.1592180751],"iteration":909,"passed_time":9.601650161,"remaining_time":0.9496137522},
{"learn":[0.1591300265],"iteration":910,"passed_time":9.610401441,"remaining_time":0.9388866392},
{"learn":[0.159025357],"iteration":911,"passed_time":9.617837393,"remaining_time":0.9280369414},
{"learn":[0.1589735768],"iteration":912,"passed_time":9.625781537,"remaining_time":0.9172431475},
{"learn":[0.1589142486],"iteration":913,"passed_time":9.63362841,"remaining_time":0.9064464369},
{"learn":[0.1588442422],"iteration":914,"passed_time":9.641515261,"remaining_time":0.8956598877},
{"learn":[0.1587682335],"iteration":915,"passed_time":9.649431804,"remaining_time":0.8848823925},
{"learn":[0.1587239651],"iteration":916,"passed_time":9.657400932,"remaining_time":0.8741158968},
{"learn":[0.1586532205],"iteration":917,"passed_time":9.666200655,"remaining_time":0.8634296882},
{"learn":[0.1585768122],"iteration":918,"passed_time":9.674279948,"remaining_time":0.8526840868},
{"learn":[0.1584559809],"iteration":919,"passed_time":9.681980604,"remaining_time":0.8419113569},
{"learn":[0.1583736632],"iteration":920,"passed_time":9.689620232,"remaining_time":0.8311400633},
{"learn":[0.1582992997],"iteration":921,"passed_time":9.696971895,"remaining_time":0.8203512015},
{"learn":[0.1582128401],"iteration":922,"passed_time":9.704731152,"remaining_time":0.8096037906},
{"learn":[0.1581591878],"iteration":923,"passed_time":9.71182095,"remaining_time":0.7988077837},
{"learn":[0.1581007834],"iteration":924,"passed_time":9.71977566,"remaining_time":0.7880899184},
{"learn":[0.1580170374],"iteration":925,"passed_time":9.727401241,"remaining_time":0.7773517191},
{"learn":[0.1579333222],"iteration":926,"passed_time":9.734925498,"remaining_time":0.766612256},
{"learn":[0.1578578701],"iteration":927,"passed_time":9.743644604,"remaining_time":0.7559724262},
{"learn":[0.1577603676],"iteration":928,"passed_time":9.75162608,"remaining_time":0.745280357},
{"learn":[0.1577060144],"iteration":929,"passed_time":9.759686043,"remaining_time":0.7346000247},
{"learn":[0.1576204714],"iteration":930,"passed_time":9.767241388,"remaining_time":0.7238879225},
{"learn":[0.1575339781],"iteration":931,"passed_time":9.77543468,"remaining_time":0.7132291398},
{"learn":[0.1574561317],"iteration":932,"passed_time":9.782863336,"remaining_time":0.7025207326},
{"learn":[0.1573973047],"iteration":933,"passed_time":9.791414606,"remaining_time":0.6918986766},
{"learn":[0.1573136202],"iteration":934,"passed_time":9.799006401,"remaining_time":0.6812143487},
{"learn":[0.1572049704],"iteration":935,"passed_time":9.807720914,"remaining_time":0.6706133959},
{"learn":[0.1571321075],"iteration":936,"passed_time":9.815480968,"remaining_time":0.6599522956},
{"learn":[0.1570861228],"iteration":937,"passed_time":9.823520261,"remaining_time":0.6493158381},
{"learn":[0.1569997005],"iteration":938,"passed_time":9.831463113,"remaining_time":0.6386786474},
{"learn":[0.1569656222],"iteration":939,"passed_time":9.839538966,"remaining_time":0.6280556787},
{"learn":[0.1568660399],"iteration":940,"passed_time":9.847581862,"remaining_time":0.6174360572},
{"learn":[0.1568075127],"iteration":941,"passed_time":9.855731626,"remaining_time":0.6068284866},
{"learn":[0.1566754129],"iteration":942,"passed_time":9.863645604,"remaining_time":0.5962118764},
{"learn":[0.1565867044],"iteration":943,"passed_time":9.871693916,"remaining_time":0.5856089611},
{"learn":[0.1565312967],"iteration":944,"passed_time":9.879400407,"remaining_time":0.5749915581},
{"learn":[0.1564434441],"iteration":945,"passed_time":9.887966491,"remaining_time":0.5644293769},
{"learn":[0.1563879232],"iteration":946,"passed_time":9.895388509,"remaining_time":0.5538073822},
{"learn":[0.1563185169],"iteration":947,"passed_time":9.903617125,"remaining_time":0.5432363824},
{"learn":[0.156236022],"iteration":948,"passed_time":9.911371466,"remaining_time":0.5326448312},
{"learn":[0.1561300925],"iteration":949,"passed_time":9.919512234,"remaining_time":0.5220795912},
{"learn":[0.1560279833],"iteration":950,"passed_time":9.927952688,"remaining_time":0.5115348914},
{"learn":[0.1559159932],"iteration":951,"passed_time":9.939260196,"remaining_time":0.5011391696},
{"learn":[0.1558397317],"iteration":952,"passed_time":9.948951971,"remaining_time":0.4906618496},
{"learn":[0.1557557078],"iteration":953,"passed_time":9.958317746,"remaining_time":0.4801704574},
{"learn":[0.1557090681],"iteration":954,"passed_time":9.966352568,"remaining_time":0.4696187074},
{"learn":[0.1556575424],"iteration":955,"passed_time":9.97519152,"remaining_time":0.4591092331},
{"learn":[0.1556261468],"iteration":956,"passed_time":9.984954233,"remaining_time":0.4486447565},
{"learn":[0.1555657205],"iteration":957,"passed_time":9.993345758,"remaining_time":0.4381216303},
{"learn":[0.1555111279],"iteration":958,"passed_time":10.00341908,"remaining_time":0.427674851},
{"learn":[0.1554495319],"iteration":959,"passed_time":10.01068256,"remaining_time":0.4171117733},
{"learn":[0.1554020359],"iteration":960,"passed_time":10.0190226,"remaining_time":0.4065992523},
{"learn":[0.1553531234],"iteration":961,"passed_time":10.02722835,"remaining_time":0.3960859432},
{"learn":[0.1552938156],"iteration":962,"passed_time":10.03754121,"remaining_time":0.385658385},
{"learn":[0.1552430323],"iteration":963,"passed_time":10.04628364,"remaining_time":0.375172418},
{"learn":[0.1551252747],"iteration":964,"passed_time":10.0545476,"remaining_time":0.364672711},
{"learn":[0.1550310947],"iteration":965,"passed_time":10.06240279,"remaining_time":0.3541632453},
{"learn":[0.1549583654],"iteration":966,"passed_time":10.0711942,"remaining_time":0.3436912188},
{"learn":[0.1548911108],"iteration":967,"passed_time":10.0794562,"remaining_time":0.3332051636},
{"learn":[0.1548163496],"iteration":968,"passed_time":10.08677492,"remaining_time":0.3226935218},
{"learn":[0.1547709667],"iteration":969,"passed_time":10.09393939,"remaining_time":0.3121836925},
{"learn":[0.1547124262],"iteration":970,"passed_time":10.10216897,"remaining_time":0.3017125645},
{"learn":[0.1546667991],"iteration":971,"passed_time":10.11010702,"remaining_time":0.2912376508},
{"learn":[0.1546246761],"iteration":972,"passed_time":10.11943963,"remaining_time":0.2808066495},
{"learn":[0.1545332231],"iteration":973,"passed_time":10.12848713,"remaining_time":0.270370293},
{"learn":[0.1544240392],"iteration":974,"passed_time":10.13750906,"remaining_time":0.2599361296},
{"learn":[0.1542913013],"iteration":975,"passed_time":10.14583671,"remaining_time":0.2494877881},
{"learn":[0.1542442807],"iteration":976,"passed_time":10.15358548,"remaining_time":0.2390301597},
{"learn":[0.154184066],"iteration":977,"passed_time":10.16252831,"remaining_time":0.2286049313},
{"learn":[0.154108072],"iteration":978,"passed_time":10.17036664,"remaining_time":0.2181590394},
{"learn":[0.1539964478],"iteration":979,"passed_time":10.17986127,"remaining_time":0.2077522707},
{"learn":[0.1539137494],"iteration":980,"passed_time":10.18802855,"remaining_time":0.1973216539},
{"learn":[0.1538344302],"iteration":981,"passed_time":10.19635033,"remaining_time":0.1868984786},
{"learn":[0.1537170892],"iteration":982,"passed_time":10.20519924,"remaining_time":0.176488695},
{"learn":[0.153635319],"iteration":983,"passed_time":10.21401119,"remaining_time":0.1660814827},
{"learn":[0.1535422684],"iteration":984,"passed_time":10.22237528,"remaining_time":0.1556706895},
{"learn":[0.1534240629],"iteration":985,"passed_time":10.23233675,"remaining_time":0.1452867287},
{"learn":[0.153351439],"iteration":986,"passed_time":10.24042917,"remaining_time":0.1348790063},
{"learn":[0.1532836174],"iteration":987,"passed_time":10.24958612,"remaining_time":0.1244889002},
{"learn":[0.1532015914],"iteration":988,"passed_time":10.25839837,"remaining_time":0.1140974541},
{"learn":[0.1531615017],"iteration":989,"passed_time":10.26699653,"remaining_time":0.1037070357},
{"learn":[0.1531020756],"iteration":990,"passed_time":10.27586075,"remaining_time":0.09332265061},
{"learn":[0.1530558068],"iteration":991,"passed_time":10.28394805,"remaining_time":0.0829350649},
{"learn":[0.1530194151],"iteration":992,"passed_time":10.29377778,"remaining_time":0.07256439521},
{"learn":[0.1529416645],"iteration":993,"passed_time":10.30230861,"remaining_time":0.06218697349},
{"learn":[0.1528914804],"iteration":994,"passed_time":10.31030678,"remaining_time":0.05181058682},
{"learn":[0.1528174292],"iteration":995,"passed_time":10.31831741,"remaining_time":0.04143902573},
{"learn":[0.15277361],"iteration":996,"passed_time":10.32609368,"remaining_time":0.03107149554},
{"learn":[0.1527317891],"iteration":997,"passed_time":10.33405934,"remaining_time":0.02070953775},
{"learn":[0.1526127665],"iteration":998,"passed_time":10.34231942,"remaining_time":0.01035267209},
{"learn":[0.1525720275],"iteration":999,"passed_time":10.34975124,"remaining_time":0}
]}